[{"chainId":42161,"address":"0x2cab3abfc1670d1a452df502e216a66883cdf079","name":"Layer2DAO","symbol":"L2DAO","decimals":18,"logoURI":"https://assets.coingecko.com/coins/images/23699/thumb/Khp7Y4Sn.png?1645081048","dexscreener":{"priceUsd":"0.005516","source":"dexscreener","liquidity":48562.68752863974},"dexguru":{"address":"0x2cab3abfc1670d1a452df502e216a66883cdf079","volume_24h":2.583815169086976,"liquidity":31.462875268889,"volume_24h_usd":3883.899187848786,"liquidity_usd":44841.021304108,"price_usd":0.005500231957036208,"volume_24h_delta":1.47836040381521,"liquidity_24h_delta":0.002341634521561068,"price_24h_delta":-0.004911802620048597,"volume_24h_delta_usd":1.3258784199680533,"liquidity_24h_delta_usd":-0.1104785932942561,"price_24h_delta_usd":-0.11915311073597808,"timestamp":1658807100},"paraswap":{"srcToken":"0x2cab3abfc1670d1a452df502e216a66883cdf079","network":42161,"destToken":"0xfd086bc7cd5c481dcc9c85ebe478a1c0b69fcbb9","destDecimals":6,"srcDecimals":18,"destAmount":"6769","srcAmount":"1000000000000000000","srcUSD":"0.0055521200","maxImpactReached":false,"priceUsd":"0.0067757690"}},{"chainId":42161,"address":"0x2ae1ef41cd23e3e77f75789e9393d8951705470f","name":"ArbiFarm","symbol":"AFARM","decimals":18,"logoURI":"https://assets.coingecko.com/coins/images/18405/thumb/DromWb7Y_400x400.jpg?1631794768","dexguru":{"address":"0x2ae1ef41cd23e3e77f75789e9393d8951705470f","volume_24h":0,"liquidity":0,"volume_24h_usd":0,"liquidity_usd":0,"price_usd":0.01535251335445569,"volume_24h_delta":-1,"liquidity_24h_delta":0,"price_24h_delta":0,"volume_24h_delta_usd":-1,"liquidity_24h_delta_usd":0,"price_24h_delta_usd":0,"timestamp":1635868641},"issue":"Inconsitent Liquidity"},{"chainId":42161,"address":"0xbe00f3db78688d9704bcb4e0a827aea3a9cc0d62","name":"Fiat24 USD","symbol":"USD24","decimals":2,"logoURI":"https://assets.coingecko.com/coins/images/25598/thumb/USD24.png?1652773795","dexguru":{"address":"0xbe00f3db78688d9704bcb4e0a827aea3a9cc0d62","volume_24h":0,"liquidity":0,"volume_24h_usd":0,"liquidity_usd":0,"price_usd":0,"volume_24h_delta":0,"liquidity_24h_delta":0,"price_24h_delta":0,"volume_24h_delta_usd":0,"liquidity_24h_delta_usd":0,"price_24h_delta_usd":0,"timestamp":1650913678},"issue":"Inconsitent Liquidity"},{"chainId":42161,"address":"0xfa42da1bd08341537a44a4ca9d236d1c00a98b40","name":"Carbon Finance","symbol":"CARBON","decimals":18,"logoURI":"https://assets.coingecko.com/coins/images/18340/thumb/EC2yLNfQ_400x400.jpg?1631596378","dexguru":{"address":"0xfa42da1bd08341537a44a4ca9d236d1c00a98b40","volume_24h":0,"liquidity":0,"volume_24h_usd":0,"liquidity_usd":0,"price_usd":0.000017877876653732363,"volume_24h_delta":-1,"liquidity_24h_delta":0,"price_24h_delta":0,"volume_24h_delta_usd":-1,"liquidity_24h_delta_usd":0,"price_24h_delta_usd":0,"timestamp":1636133101},"issue":"Inconsitent Liquidity"},{"chainId":42161,"address":"0x8fbd420956fdd301f4493500fd0bcaaa80f2389c","name":"Amy Finance","symbol":"AMY","decimals":18,"logoURI":"https://assets.coingecko.com/coins/images/18719/thumb/9oSy6bTl_400x400.png?1633127387","dexguru":{"address":"0x8fbd420956fdd301f4493500fd0bcaaa80f2389c","volume_24h":0,"liquidity":0,"volume_24h_usd":0,"liquidity_usd":0,"price_usd":0.0001839338958160491,"volume_24h_delta":0,"liquidity_24h_delta":0,"price_24h_delta":0,"volume_24h_delta_usd":0,"liquidity_24h_delta_usd":0,"price_24h_delta_usd":0,"timestamp":1634363866},"issue":"Inconsitent Liquidity"},{"chainId":42161,"address":"0xcfe3fbc98d80f7eca0bc76cd1f406a19dd425896","name":"Scalara NFT Index","symbol":"NFTI","decimals":18,"logoURI":"https://assets.coingecko.com/coins/images/23647/thumb/NFTI-logo-white-bg.png?1644910969","dexscreener":null,"dexguru":{"address":"0xcfe3fbc98d80f7eca0bc76cd1f406a19dd425896","volume_24h":0,"liquidity":65.774576364973,"volume_24h_usd":0,"liquidity_usd":100256.91368215,"price_usd":5.152364110023542,"volume_24h_delta":-1,"liquidity_24h_delta":0,"price_24h_delta":0,"volume_24h_delta_usd":-1,"liquidity_24h_delta_usd":0,"price_24h_delta_usd":0,"timestamp":1658609400},"paraswap":null},{"chainId":42161,"address":"0x64343594ab9b56e99087bfa6f2335db24c2d1f17","name":"Vesta Stable","symbol":"VST","decimals":18,"logoURI":"https://assets.coingecko.com/coins/images/23621/thumb/vesta.png?1644809642","dexscreener":{"priceUsd":"1.00","source":"dexscreener","liquidity":193082},"dexguru":{"address":"0x64343594ab9b56e99087bfa6f2335db24c2d1f17","volume_24h":32.124184205722536,"liquidity":3612.0012859789,"volume_24h_usd":48941.1723751324,"liquidity_usd":5125061.2516896,"price_usd":1.0057229361780196,"volume_24h_delta":-0.4356502926681891,"liquidity_24h_delta":0.10289561634668763,"price_24h_delta":0.08580538411202947,"volume_24h_delta_usd":-0.4586528152270013,"liquidity_24h_delta_usd":0.01569064429862666,"price_24h_delta_usd":-0.0000482785263131965,"timestamp":1658805180},"paraswap":{"srcToken":"0x64343594ab9b56e99087bfa6f2335db24c2d1f17","network":42161,"destToken":"0xfd086bc7cd5c481dcc9c85ebe478a1c0b69fcbb9","destDecimals":6,"srcDecimals":18,"destAmount":"1006599","srcAmount":"1000000000000000000","srcUSD":"1.0023272111","maxImpactReached":false,"priceUsd":"1.0076055990"}},{"chainId":42161,"address":"0x0c4681e6c0235179ec3d4f4fc4df3d14fdd96017","name":"Radiant Capital","symbol":"RDNT","decimals":18,"logoURI":"https://assets.coingecko.com/coins/images/26536/thumb/Radiant-Logo-200x200.png?1658715865","dexscreener":{"priceUsd":"0.2024","source":"dexscreener","liquidity":4633354.026669716},"dexguru":{"address":"0x0c4681e6c0235179ec3d4f4fc4df3d14fdd96017","volume_24h":972.6356577987106,"liquidity":1620.9092939943,"volume_24h_usd":1440622.692544818,"liquidity_usd":2325808.7644971,"price_usd":0.2028584106270239,"volume_24h_delta":0.11171020324193555,"liquidity_24h_delta":0.49054596065130057,"price_24h_delta":0.7201919051590687,"volume_24h_delta_usd":0.04499506548960876,"liquidity_24h_delta_usd":0.40956842000617183,"price_24h_delta_usd":0.6267356512893413,"timestamp":1658808420},"paraswap":{"srcToken":"0x0c4681e6c0235179ec3d4f4fc4df3d14fdd96017","network":42161,"destToken":"0xfd086bc7cd5c481dcc9c85ebe478a1c0b69fcbb9","destDecimals":6,"srcDecimals":18,"destAmount":"200701","srcAmount":"1000000000000000000","srcUSD":"0.1985990000","maxImpactReached":false,"priceUsd":"0.2009017010"}},{"chainId":42161,"address":"0x6ba4edd6db54ed34d53d8d8883e599c4dba009fb","name":"L2PAD","symbol":"L2PAD","decimals":18,"logoURI":"https://assets.coingecko.com/coins/images/23694/thumb/l2pad_200x200.png?1645080419","dexguru":{"address":"0x6ba4edd6db54ed34d53d8d8883e599c4dba009fb","volume_24h":0,"liquidity":2.8694449310646,"volume_24h_usd":0,"liquidity_usd":4448.5156347264,"price_usd":0.1464028227822874,"volume_24h_delta":-1,"liquidity_24h_delta":0,"price_24h_delta":0,"volume_24h_delta_usd":-1,"liquidity_24h_delta_usd":0,"price_24h_delta_usd":0,"timestamp":1658311560},"issue":"Inconsitent Liquidity"},{"chainId":42161,"address":"0x9e724698051da34994f281bd81c3e7372d1960ae","name":"Ascension Protocol","symbol":"ASCEND","decimals":18,"logoURI":"https://assets.coingecko.com/coins/images/16019/thumb/icon200.png?1622612188","dexscreener":null,"dexguru":{"address":"0x9e724698051da34994f281bd81c3e7372d1960ae","volume_24h":0,"liquidity":57.12327792938,"volume_24h_usd":0,"liquidity_usd":87906.438355983,"price_usd":0.020578546715759687,"volume_24h_delta":0,"liquidity_24h_delta":0,"price_24h_delta":0,"volume_24h_delta_usd":0,"liquidity_24h_delta_usd":0,"price_24h_delta_usd":0,"timestamp":1658537340},"paraswap":{"srcToken":"0x9e724698051da34994f281bd81c3e7372d1960ae","network":42161,"destToken":"0xfd086bc7cd5c481dcc9c85ebe478a1c0b69fcbb9","destDecimals":6,"srcDecimals":18,"destAmount":"19103","srcAmount":"1000000000000000000","srcUSD":"0.0209377400","maxImpactReached":false,"priceUsd":"0.0191221030"}},{"chainId":42161,"address":"0xfc5a1a6eb076a2c7ad06ed22c90d7e710e35ad0a","name":"GMX","symbol":"GMX","decimals":18,"logoURI":"https://assets.coingecko.com/coins/images/18323/thumb/arbit.png?1631532468","dexscreener":{"priceUsd":"23.84","source":"dexscreener","liquidity":635774},"dexguru":{"address":"0xfc5a1a6eb076a2c7ad06ed22c90d7e710e35ad0a","volume_24h":609.9851340319826,"liquidity":4793.3810008464,"volume_24h_usd":913931.3572018313,"liquidity_usd":6856281.5867728,"price_usd":23.9730869342479,"volume_24h_delta":-0.14789836428189082,"liquidity_24h_delta":-0.033731281515580976,"price_24h_delta":-0.03146031339535963,"volume_24h_delta_usd":-0.19755531663130338,"liquidity_24h_delta_usd":-0.08514369689638243,"price_24h_delta_usd":-0.08017055545465114,"timestamp":1658807820},"paraswap":{"srcToken":"0xfc5a1a6eb076a2c7ad06ed22c90d7e710e35ad0a","network":42161,"destToken":"0xfd086bc7cd5c481dcc9c85ebe478a1c0b69fcbb9","destDecimals":6,"srcDecimals":18,"destAmount":"24224321","srcAmount":"1000000000000000000","srcUSD":"24.0600000000","maxImpactReached":false,"priceUsd":"24.2485453210"}},{"chainId":42161,"address":"0x86a1012d437bbff84fbdf62569d12d4fd3396f8c","name":"Arbys","symbol":"ARBYS","decimals":18,"logoURI":"https://assets.coingecko.com/coins/images/18332/thumb/arby.PNG?1631579212","dexguru":{"address":"0x86a1012d437bbff84fbdf62569d12d4fd3396f8c","volume_24h":0,"liquidity":4.554967353695,"volume_24h_usd":0,"liquidity_usd":6128.5432851623,"price_usd":0.13183834891908092,"volume_24h_delta":0,"liquidity_24h_delta":0,"price_24h_delta":0,"volume_24h_delta_usd":0,"liquidity_24h_delta_usd":0,"price_24h_delta_usd":0,"timestamp":1657988640},"issue":"Inconsitent Liquidity"},{"chainId":42161,"address":"0xa4f595ba35161c9ffe3db8c03991b9c2cbb26c6b","name":"LYS Capital","symbol":"LYS","decimals":18,"logoURI":"https://assets.coingecko.com/coins/images/20863/thumb/1637613107-lys-logo-cg-200pix.png?1637805637","dexscreener":{"priceUsd":"0.00325","source":"dexscreener","liquidity":31137.594438},"dexguru":{"address":"0xa4f595ba35161c9ffe3db8c03991b9c2cbb26c6b","volume_24h":0,"liquidity":10.98363300074,"volume_24h_usd":0,"liquidity_usd":15568.797219,"price_usd":0.003259608132642435,"volume_24h_delta":-1,"liquidity_24h_delta":0,"price_24h_delta":0,"volume_24h_delta_usd":-1,"liquidity_24h_delta_usd":0,"price_24h_delta_usd":0,"timestamp":1658798580},"paraswap":{"srcToken":"0xa4f595ba35161c9ffe3db8c03991b9c2cbb26c6b","network":42161,"destToken":"0xfd086bc7cd5c481dcc9c85ebe478a1c0b69fcbb9","destDecimals":6,"srcDecimals":18,"destAmount":"3230","srcAmount":"1000000000000000000","srcUSD":"0.0032525000","maxImpactReached":false,"priceUsd":"0.0032332300"}},{"chainId":42161,"address":"0xde31e75182276738b0c025daa8f80020a4f2fbfe","name":"Honey Pot BeeKeepers","symbol":"HONEY","decimals":18,"logoURI":"https://assets.coingecko.com/coins/images/18380/thumb/ac6fTCfDQDIV.jpg?1631695015","dexguru":{"address":"0xde31e75182276738b0c025daa8f80020a4f2fbfe","volume_24h":0.03175774296165929,"liquidity":2.4815052055232,"volume_24h_usd":46.452317904741626,"liquidity_usd":3528.152522835,"price_usd":0.00006559034268245746,"volume_24h_delta":-0.5264272916169694,"liquidity_24h_delta":0.021378378567923642,"price_24h_delta":0.02123506756913617,"volume_24h_delta_usd":-0.5639495314403402,"liquidity_24h_delta_usd":-0.02797269798993021,"price_24h_delta_usd":-0.015624431747948241,"timestamp":1658805120},"issue":"Inconsitent Liquidity"},{"chainId":42161,"address":"0xb5de3f06af62d8428a8bf7b4400ea42ad2e0bc53","name":"Brinc Finance","symbol":"BRC","decimals":18,"logoURI":"https://assets.coingecko.com/coins/images/26116/thumb/76469697.png?1655937532","dexscreener":null,"dexguru":{"address":"0xb5de3f06af62d8428a8bf7b4400ea42ad2e0bc53","volume_24h":0,"liquidity":17.763951961981,"volume_24h_usd":0,"liquidity_usd":33290.078339561,"price_usd":0.5169530843310048,"volume_24h_delta":0,"liquidity_24h_delta":0,"price_24h_delta":0,"volume_24h_delta_usd":0,"liquidity_24h_delta_usd":0,"price_24h_delta_usd":0,"timestamp":1654491120},"paraswap":null},{"chainId":42161,"address":"0xa684cd057951541187f288294a1e1c2646aa2d24","name":"Vesta Finance","symbol":"VSTA","decimals":18,"logoURI":"https://assets.coingecko.com/coins/images/23306/thumb/vesta-finance.png?1643692530","dexguru":{"address":"0xa684cd057951541187f288294a1e1c2646aa2d24","volume_24h":0,"liquidity":0.50469475288698,"volume_24h_usd":0,"liquidity_usd":1193.5920028225,"price_usd":0.5228301604417122,"volume_24h_delta":-1,"liquidity_24h_delta":0,"price_24h_delta":0,"volume_24h_delta_usd":-1,"liquidity_24h_delta_usd":0,"price_24h_delta_usd":0,"timestamp":1643815438},"issue":"Inconsitent Liquidity"},{"chainId":42161,"address":"0x155f0dd04424939368972f4e1838687d6a831151","name":"ArbiDoge","symbol":"ADOGE","decimals":18,"logoURI":"https://assets.coingecko.com/coins/images/18333/thumb/Screen-Shot-2021-09-04-at-11-59-16-AM.png?1631584395","dexscreener":{"priceUsd":"0.0000000116","source":"dexscreener","liquidity":40397.00113466196},"dexguru":{"address":"0x155f0dd04424939368972f4e1838687d6a831151","volume_24h":0,"liquidity":13.22942054649,"volume_24h_usd":0,"liquidity_usd":20107.985155948,"price_usd":1.1518645513421298e-8,"volume_24h_delta":-1,"liquidity_24h_delta":0,"price_24h_delta":0,"volume_24h_delta_usd":-1,"liquidity_24h_delta_usd":0,"price_24h_delta_usd":0,"timestamp":1658765820},"paraswap":null},{"chainId":42161,"address":"0xd74f5255d557944cf7dd0e45ff521520002d5748","name":"Sperax USD","symbol":"USDS","decimals":18,"logoURI":"https://assets.coingecko.com/coins/images/21973/thumb/USDs_logo_1000X1000.png?1640565887","dexscreener":{"priceUsd":"0.9988","source":"dexscreener","liquidity":4946534},"dexguru":{"address":"0xd74f5255d557944cf7dd0e45ff521520002d5748","volume_24h":1.3367915445271825,"liquidity":2333.2616766992,"volume_24h_usd":2039.6631711897596,"liquidity_usd":3326977.4987172,"price_usd":0.9983854202367354,"volume_24h_delta":2.1136183707731293,"liquidity_24h_delta":0.05844080908197649,"price_24h_delta":0.06311270115813201,"volume_24h_delta_usd":1.9881294693039329,"liquidity_24h_delta_usd":-0.001959282211821674,"price_24h_delta_usd":-0.0000498414719787948,"timestamp":1658797920},"paraswap":null},{"chainId":42161,"address":"0xc136e6b376a9946b156db1ed3a34b08afdaed76d","name":"CreDA","symbol":"CREDA","decimals":18,"logoURI":"https://assets.coingecko.com/coins/images/22551/thumb/gZ4EgSXD_400x400.jpg?1642053045","dexscreener":{"priceUsd":"0.2004","source":"dexscreener","liquidity":104916.16294095824},"dexguru":{"address":"0xc136e6b376a9946b156db1ed3a34b08afdaed76d","volume_24h":0.24861466795835227,"liquidity":15.151681768312,"volume_24h_usd":377.92070971548225,"liquidity_usd":21611.353791768,"price_usd":0.20247929208558735,"volume_24h_delta":0.1952174435455426,"liquidity_24h_delta":0.00865019401193137,"price_24h_delta":-0.008548169515573247,"volume_24h_delta_usd":0.13608148722031452,"liquidity_24h_delta_usd":-0.017354385974452425,"price_24h_delta_usd":-0.034109348784165716,"timestamp":1658801100},"paraswap":{"srcToken":"0xc136e6b376a9946b156db1ed3a34b08afdaed76d","network":42161,"destToken":"0xfd086bc7cd5c481dcc9c85ebe478a1c0b69fcbb9","destDecimals":6,"srcDecimals":18,"destAmount":"201838","srcAmount":"1000000000000000000","srcUSD":"0.2052670000","maxImpactReached":false,"priceUsd":"0.2020398380"}},{"chainId":42161,"address":"0xf0b5ceefc89684889e5f7e0a7775bd100fcd3709","name":"DigitalDollar","symbol":"DUSD","decimals":6,"logoURI":"https://assets.coingecko.com/coins/images/23731/thumb/icon_dusd_2_kvy1zn.png?1645170317","dexscreener":null,"dexguru":{"address":"0xf0b5ceefc89684889e5f7e0a7775bd100fcd3709","volume_24h":0,"liquidity":326.33165288011,"volume_24h_usd":0,"liquidity_usd":956787.72248263,"price_usd":1.0790714183156667,"volume_24h_delta":-1,"liquidity_24h_delta":0,"price_24h_delta":0,"volume_24h_delta_usd":-1,"liquidity_24h_delta_usd":0,"price_24h_delta_usd":0,"timestamp":1644860293},"paraswap":{"srcToken":"0xf0b5ceefc89684889e5f7e0a7775bd100fcd3709","network":42161,"destToken":"0xfd086bc7cd5c481dcc9c85ebe478a1c0b69fcbb9","destDecimals":6,"srcDecimals":6,"destAmount":"1263139","srcAmount":"1000000","srcUSD":"0.7457220000","maxImpactReached":false,"priceUsd":"1.2644021390"}},{"chainId":42161,"address":"0xb41bd4c99da73510d9e081c5fadbe7a27ac1f814","name":"Ideamarket","symbol":"IMO","decimals":18,"logoURI":"https://assets.coingecko.com/coins/images/23330/thumb/6189656aa934fd0f709d1121_favilg.png?1643852444","dexscreener":{"priceUsd":"0.1179","source":"dexscreener","liquidity":4.274812},"dexguru":{"address":"0xb41bd4c99da73510d9e081c5fadbe7a27ac1f814","volume_24h":0,"liquidity":18.634806627829,"volume_24h_usd":0,"liquidity_usd":28167.851194611,"price_usd":0.024173593501529773,"volume_24h_delta":-1,"liquidity_24h_delta":0,"price_24h_delta":0,"volume_24h_delta_usd":-1,"liquidity_24h_delta_usd":0,"price_24h_delta_usd":0,"timestamp":1658737860},"paraswap":{"srcToken":"0xb41bd4c99da73510d9e081c5fadbe7a27ac1f814","network":42161,"destToken":"0xfd086bc7cd5c481dcc9c85ebe478a1c0b69fcbb9","destDecimals":6,"srcDecimals":18,"destAmount":"22845","srcAmount":"1000000000000000000","srcUSD":"0.0243782700","maxImpactReached":false,"priceUsd":"0.0228678450"}},{"chainId":42161,"address":"0xafd871f684f21ab9d7137608c71808f83d75e6fc","name":"Arbucks","symbol":"BUCK","decimals":18,"logoURI":"https://assets.coingecko.com/coins/images/18357/thumb/arbucks.png?1632293927","dexguru":{"address":"0xafd871f684f21ab9d7137608c71808f83d75e6fc","volume_24h":0,"liquidity":3.8627955743999,"volume_24h_usd":0,"liquidity_usd":5869.6545229072,"price_usd":0.00018768982597110957,"volume_24h_delta":0,"liquidity_24h_delta":0,"price_24h_delta":0,"volume_24h_delta_usd":0,"liquidity_24h_delta_usd":0,"price_24h_delta_usd":0,"timestamp":1658727240},"issue":"Inconsitent Liquidity"},{"chainId":42161,"address":"0x0f4676178b5c53ae0a655f1b19a96387e4b8b5f2","name":"Cudl Finance","symbol":"CUDL","decimals":18,"logoURI":"https://assets.coingecko.com/coins/images/17479/thumb/cudl.PNG?1627950486","dexguru":{"address":"0x0f4676178b5c53ae0a655f1b19a96387e4b8b5f2","volume_24h":0,"liquidity":0.93623752835903,"volume_24h_usd":0,"liquidity_usd":1018.308506736,"price_usd":0.005404556441220137,"volume_24h_delta":-1,"liquidity_24h_delta":0,"price_24h_delta":0,"volume_24h_delta_usd":-1,"liquidity_24h_delta_usd":0,"price_24h_delta_usd":0,"timestamp":1655870400},"issue":"Inconsitent Liquidity"},{"chainId":42161,"address":"0xed3fb761414da74b74f33e5c5a1f78104b188dfc","name":"ArbiNYAN","symbol":"NYAN","decimals":18,"logoURI":"https://assets.coingecko.com/coins/images/18309/thumb/Qmf8DSV4RbSuVRLJvmj4WwEMjwtYcCd53EFXPPjkEwzx4B.png?1631508598","dexscreener":null,"dexguru":{"address":"0xed3fb761414da74b74f33e5c5a1f78104b188dfc","volume_24h":0.04490058957326633,"liquidity":8.0722696576515,"volume_24h_usd":72.27896266635362,"liquidity_usd":12269.854968177,"price_usd":0.0008428337798874002,"volume_24h_delta":37.64882062647328,"liquidity_24h_delta":-0.005448288677472679,"price_24h_delta":-0.010883109135382993,"volume_24h_delta_usd":38.678434557584254,"liquidity_24h_delta_usd":0.021046809506326963,"price_24h_delta_usd":0.015467204116706487,"timestamp":1658716320},"paraswap":null},{"chainId":42161,"address":"0x10393c20975cf177a3513071bc110f7962cd67da","name":"Jones DAO","symbol":"JONES","decimals":18,"logoURI":"https://assets.coingecko.com/coins/images/23290/thumb/3c8c2ed8-afb3-4b67-9937-5493acd88b50.jpg?1648597625","dexscreener":{"priceUsd":"0.8687","source":"dexscreener","liquidity":1453033.1858283463},"dexguru":{"address":"0x10393c20975cf177a3513071bc110f7962cd67da","volume_24h":18.641064379874493,"liquidity":517.49833287162,"volume_24h_usd":27727.23888555378,"liquidity_usd":738748.35921014,"price_usd":0.8681164799192008,"volume_24h_delta":0.3295457765904511,"liquidity_24h_delta":-0.038120646127608196,"price_24h_delta":-0.08532152892776262,"volume_24h_delta_usd":0.24245236319728458,"liquidity_24h_delta_usd":-0.0914447760063001,"price_24h_delta_usd":-0.13588104808669801,"timestamp":1658806560},"paraswap":{"srcToken":"0x10393c20975cf177a3513071bc110f7962cd67da","network":42161,"destToken":"0xfd086bc7cd5c481dcc9c85ebe478a1c0b69fcbb9","destDecimals":6,"srcDecimals":18,"destAmount":"868474","srcAmount":"1000000000000000000","srcUSD":"0.8694510000","maxImpactReached":false,"priceUsd":"0.8693424740"}},{"chainId":42161,"address":"0x2c110867ca90e43d372c1c2e92990b00ea32818b","name":"Stabilize","symbol":"STBZ","decimals":18,"logoURI":"https://assets.coingecko.com/coins/images/12753/thumb/icon.png?1608771101","dexscreener":null,"dexguru":{"address":"0x2c110867ca90e43d372c1c2e92990b00ea32818b","volume_24h":0.22938676027514546,"liquidity":7.9902426200939,"volume_24h_usd":248.7398466372857,"liquidity_usd":12824.596516118,"price_usd":0.1753096030952809,"volume_24h_delta":1,"liquidity_24h_delta":-0.026600967455626713,"price_24h_delta":-0.05257586029917504,"volume_24h_delta_usd":1,"liquidity_24h_delta_usd":-0.14274135775495947,"price_24h_delta_usd":-0.16561707534563117,"timestamp":1658676840},"paraswap":{"srcToken":"0x2c110867ca90e43d372c1c2e92990b00ea32818b","network":42161,"destToken":"0xfd086bc7cd5c481dcc9c85ebe478a1c0b69fcbb9","destDecimals":6,"srcDecimals":18,"destAmount":"156030","srcAmount":"1000000000000000000","srcUSD":"0.1764160000","maxImpactReached":false,"priceUsd":"0.1561860300"}},{"chainId":42161,"address":"0xeb6f8eebc83d85120f9299b84da558825685570e","name":"ArbiRiseFinance","symbol":"ARF","decimals":9,"logoURI":"https://assets.coingecko.com/coins/images/20860/thumb/profile_picture_200.png?1637803349","dexguru":{"address":"0xeb6f8eebc83d85120f9299b84da558825685570e","volume_24h":0,"liquidity":1.4860882545048,"volume_24h_usd":0,"liquidity_usd":1777.7751553773,"price_usd":0.0000042677761813558164,"volume_24h_delta":-1,"liquidity_24h_delta":0,"price_24h_delta":0,"volume_24h_delta_usd":-1,"liquidity_24h_delta_usd":0,"price_24h_delta_usd":0,"timestamp":1656376140},"issue":"Inconsitent Liquidity"},{"chainId":42161,"address":"0xa7e1d00f1dc94040a8aad3ad993589f3e39a6b7a","name":"ArbiMATTER","symbol":"ARBIMATTER","decimals":9,"logoURI":"https://assets.coingecko.com/coins/images/18479/thumb/1.jpg?1632149187","dexscreener":null,"dexguru":{"address":"0xa7e1d00f1dc94040a8aad3ad993589f3e39a6b7a","volume_24h":0,"liquidity":11.179714487977,"volume_24h_usd":0,"liquidity_usd":11791.334315425,"price_usd":0.000009060749214456211,"volume_24h_delta":0,"liquidity_24h_delta":1,"price_24h_delta":1,"volume_24h_delta_usd":0,"liquidity_24h_delta_usd":1,"price_24h_delta_usd":1,"timestamp":1656909480},"paraswap":{"srcToken":"0xa7e1d00f1dc94040a8aad3ad993589f3e39a6b7a","network":42161,"destToken":"0xfd086bc7cd5c481dcc9c85ebe478a1c0b69fcbb9","destDecimals":6,"srcDecimals":9,"destAmount":"12","srcAmount":"1000000000","srcUSD":"0.0000094900","maxImpactReached":false,"priceUsd":"0.0000120120"}},{"chainId":42161,"address":"0xd3f1da62cafb7e7bc6531ff1cef6f414291f03d3","name":"Doubloon","symbol":"DBL","decimals":18,"logoURI":"https://assets.coingecko.com/coins/images/23660/thumb/galleon-sky.png?1651744892","dexscreener":{"priceUsd":"0.0294","source":"dexscreener","liquidity":276523},"dexguru":{"address":"0xd3f1da62cafb7e7bc6531ff1cef6f414291f03d3","volume_24h":0.4105164330719023,"liquidity":33.481516231849,"volume_24h_usd":591.7449199281132,"liquidity_usd":48253.81473204,"price_usd":0.029404053862580517,"volume_24h_delta":20209.59447920759,"liquidity_24h_delta":0.0044474063720543735,"price_24h_delta":0.008907026606695291,"volume_24h_delta_usd":18165.463423983936,"liquidity_24h_delta_usd":-0.09742405006252666,"price_24h_delta_usd":-0.09341672629016558,"timestamp":1658794320},"paraswap":null},{"chainId":42161,"address":"0x9f20de1fc9b161b34089cbeae888168b44b03461","name":"Arbis Finance","symbol":"ARBIS","decimals":18,"logoURI":"https://assets.coingecko.com/coins/images/18594/thumb/NcAIaWlc_400x400_%281%29.jpg?1632608958","dexscreener":null,"dexguru":{"address":"0x9f20de1fc9b161b34089cbeae888168b44b03461","volume_24h":0.12833534066985688,"liquidity":65.591372911798,"volume_24h_usd":204.46766826658558,"liquidity_usd":76029.814528082,"price_usd":0.000051934670391282615,"volume_24h_delta":1,"liquidity_24h_delta":-0.0002066813053699883,"price_24h_delta":0.00023755610428039043,"volume_24h_delta_usd":1,"liquidity_24h_delta_usd":0.004934726654751505,"price_24h_delta_usd":0.0037480456066781532,"timestamp":1658653020},"paraswap":{"srcToken":"0x9f20de1fc9b161b34089cbeae888168b44b03461","network":42161,"destToken":"0xfd086bc7cd5c481dcc9c85ebe478a1c0b69fcbb9","destDecimals":6,"srcDecimals":18,"destAmount":"46","srcAmount":"1000000000000000000","srcUSD":"0.0000494500","maxImpactReached":false,"priceUsd":"0.0000460460"}},{"chainId":42161,"address":"0x86b3353387f560295a8fa7902679735e5f076bd5","name":"Omicron","symbol":"OMIC","decimals":9,"logoURI":"https://assets.coingecko.com/coins/images/19954/thumb/YHCCP1e.png?1636339997","dexscreener":{"priceUsd":"1.71","source":"dexscreener","liquidity":19765.856525518375},"dexguru":{"address":"0x86b3353387f560295a8fa7902679735e5f076bd5","volume_24h":0.14007830499615578,"liquidity":12.79149706716,"volume_24h_usd":211.16289196533583,"liquidity_usd":19005.679764117,"price_usd":1.7095541028682886,"volume_24h_delta":1,"liquidity_24h_delta":0.014750447095003116,"price_24h_delta":0.015731266867107296,"volume_24h_delta_usd":1,"liquidity_24h_delta_usd":-0.006779324796737714,"price_24h_delta_usd":-0.011449534122359543,"timestamp":1658791620},"paraswap":{"srcToken":"0x86b3353387f560295a8fa7902679735e5f076bd5","network":42161,"destToken":"0xfd086bc7cd5c481dcc9c85ebe478a1c0b69fcbb9","destDecimals":6,"srcDecimals":9,"destAmount":"1712123","srcAmount":"1000000000","srcUSD":"1.7200000000","maxImpactReached":false,"priceUsd":"1.7138351230"}},{"chainId":42161,"address":"0x876ec6be52486eeec06bc06434f3e629d695c6ba","name":"FluidFi","symbol":"FLUID","decimals":18,"logoURI":"https://assets.coingecko.com/coins/images/20428/thumb/FluidFi_Logo_32x32px_vtvcai.png?1637032506","dexscreener":{"priceUsd":"0.2951","source":"dexscreener","liquidity":348071.9591913655},"dexguru":{"address":"0x876ec6be52486eeec06bc06434f3e629d695c6ba","volume_24h":5.856407938226333,"liquidity":114.7069663569,"volume_24h_usd":9091.915959042812,"liquidity_usd":173551.80023383,"price_usd":0.2927030710085551,"volume_24h_delta":5.199036004415531,"liquidity_24h_delta":0.040395895040882195,"price_24h_delta":0.08225690369789629,"volume_24h_delta_usd":5.015980310523496,"liquidity_24h_delta_usd":-0.02507431291686644,"price_24h_delta_usd":0.01415245914311415,"timestamp":1658781000},"paraswap":{"srcToken":"0x876ec6be52486eeec06bc06434f3e629d695c6ba","network":42161,"destToken":"0xfd086bc7cd5c481dcc9c85ebe478a1c0b69fcbb9","destDecimals":6,"srcDecimals":18,"destAmount":"276364","srcAmount":"1000000000000000000","srcUSD":"0.2792610000","maxImpactReached":false,"priceUsd":"0.2766403640"}},{"chainId":42161,"address":"0x51318b7d00db7acc4026c88c3952b66278b6a67f","name":"PlutusDAO","symbol":"PLS","decimals":18,"logoURI":"https://assets.coingecko.com/coins/images/25326/thumb/M6nUndNU_400x400.jpg?1651233987","dexscreener":{"priceUsd":"0.267","source":"dexscreener","liquidity":1109480.3627810443},"dexguru":{"address":"0x51318b7d00db7acc4026c88c3952b66278b6a67f","volume_24h":25.114154188279024,"liquidity":391.20178300919,"volume_24h_usd":36147.884331287394,"liquidity_usd":555337.49850415,"price_usd":0.2666144536380472,"volume_24h_delta":-0.6496218377334712,"liquidity_24h_delta":-0.04635859845664387,"price_24h_delta":-0.08975743690240225,"volume_24h_delta_usd":-0.6803250023247898,"liquidity_24h_delta_usd":-0.10868112578838197,"price_24h_delta_usd":-0.149243756314879,"timestamp":1658803140},"paraswap":{"srcToken":"0x51318b7d00db7acc4026c88c3952b66278b6a67f","network":42161,"destToken":"0xfd086bc7cd5c481dcc9c85ebe478a1c0b69fcbb9","destDecimals":6,"srcDecimals":18,"destAmount":"268300","srcAmount":"1000000000000000000","srcUSD":"0.2699260000","maxImpactReached":false,"priceUsd":"0.2685683000"}},{"chainId":42161,"address":"0xf4fe727c855c2d395852ca43f645cab4b504af23","name":"Hydranet","symbol":"HDX","decimals":9,"logoURI":"https://assets.coingecko.com/coins/images/25177/thumb/HDXdarkblueInv.png?1652694650","dexguru":{"address":"0xf4fe727c855c2d395852ca43f645cab4b504af23","volume_24h":0.5952136704486136,"liquidity":2.8482107967674,"volume_24h_usd":886.6004934675018,"liquidity_usd":4049.8644674435,"price_usd":0.011214613662460323,"volume_24h_delta":-0.19008255835454035,"liquidity_24h_delta":0.15372742400567543,"price_24h_delta":0.10336994458741218,"volume_24h_delta_usd":-0.24622267603886178,"liquidity_24h_delta_usd":0.03410406743786316,"price_24h_delta_usd":-0.01945626312503838,"timestamp":1658802420},"issue":"Inconsitent Liquidity"},{"chainId":42161,"address":"0xdb96f8efd6865644993505318cc08ff9c42fb9ac","name":"ZeroTwOhm","symbol":"Z2O","decimals":9,"logoURI":"https://assets.coingecko.com/coins/images/19508/thumb/z2o.jpg?1635825988","dexguru":{"address":"0xdb96f8efd6865644993505318cc08ff9c42fb9ac","volume_24h":0,"liquidity":1.0325306095397,"volume_24h_usd":0,"liquidity_usd":1100.3075378304,"price_usd":13.467980068994834,"volume_24h_delta":0,"liquidity_24h_delta":0,"price_24h_delta":0,"volume_24h_delta_usd":0,"liquidity_24h_delta_usd":0,"price_24h_delta_usd":0,"timestamp":1656796860},"issue":"Inconsitent Liquidity"},{"chainId":42161,"address":"0x1622bf67e6e5747b81866fe0b85178a93c7f86e3","name":"Umami Finance","symbol":"UMAMI","decimals":9,"logoURI":"https://assets.coingecko.com/coins/images/21159/thumb/1_ax54JNAAQWm7HE1ehAQV5g.png?1638414189","dexscreener":{"priceUsd":"21.91","source":"dexscreener","liquidity":1179515},"dexguru":{"address":"0x1622bf67e6e5747b81866fe0b85178a93c7f86e3","volume_24h":52.33171982849087,"liquidity":638.37720499312,"volume_24h_usd":78190.38697345182,"liquidity_usd":875432.59639437,"price_usd":21.66158048719607,"volume_24h_delta":0.3417076071503649,"liquidity_24h_delta":0.059031288861835375,"price_24h_delta":0.009374114893160266,"volume_24h_delta_usd":0.2512632802749448,"liquidity_24h_delta_usd":0.004318731729450616,"price_24h_delta_usd":-0.06261397231343452,"timestamp":1658806320},"paraswap":null},{"chainId":42161,"address":"0x2c852d3334188be136bfc540ef2bb8c37b590bad","name":"MagicLand","symbol":"MAGIC","decimals":18,"logoURI":"https://assets.coingecko.com/coins/images/18844/thumb/logo_-_2021-10-07T141625.399.png?1633587397","dexguru":{"address":"0x2c852d3334188be136bfc540ef2bb8c37b590bad","volume_24h":0.025347542646824858,"liquidity":1.6154319918044,"volume_24h_usd":38.100297101396364,"liquidity_usd":2353.5975731813,"price_usd":0.0027366120964835536,"volume_24h_delta":-0.3648201456531146,"liquidity_24h_delta":0.03846073403012579,"price_24h_delta":0.039061561957184125,"volume_24h_delta_usd":-0.4085023345929153,"liquidity_24h_delta_usd":-0.025369677083006914,"price_24h_delta_usd":-0.027612252882075326,"timestamp":1658793780},"issue":"Inconsitent Liquidity"},{"chainId":42161,"address":"0xae6aab43c4f3e0cea4ab83752c278f8debaba689","name":"dForce","symbol":"DF","decimals":18,"logoURI":"https://assets.coingecko.com/coins/images/9709/thumb/xlGxxIjI_400x400.jpg?1571006794","dexguru":{"address":"0xae6aab43c4f3e0cea4ab83752c278f8debaba689","volume_24h":0,"liquidity":0,"volume_24h_usd":0,"liquidity_usd":0,"price_usd":0,"volume_24h_delta":0,"liquidity_24h_delta":0,"price_24h_delta":0,"volume_24h_delta_usd":0,"liquidity_24h_delta_usd":0,"price_24h_delta_usd":0,"timestamp":1650913489},"issue":"Inconsitent Liquidity"},{"chainId":42161,"address":"0x080f6aed32fc474dd5717105dba5ea57268f46eb","name":"Synapse","symbol":"SYN","decimals":18,"logoURI":"https://assets.coingecko.com/coins/images/18024/thumb/syn.png?1635002049","dexguru":{"address":"0x080f6aed32fc474dd5717105dba5ea57268f46eb","volume_24h":0,"liquidity":0.75980704616691,"volume_24h_usd":0,"liquidity_usd":1021.9720686824,"price_usd":1.1363775222539625,"volume_24h_delta":-1,"liquidity_24h_delta":0,"price_24h_delta":0,"volume_24h_delta_usd":-1,"liquidity_24h_delta_usd":0,"price_24h_delta_usd":0,"timestamp":1658053560},"issue":"Inconsitent Liquidity"},{"chainId":42161,"address":"0x848e0ba28b637e8490d88bae51fa99c87116409b","name":"Agave","symbol":"AGVE","decimals":18,"logoURI":"https://assets.coingecko.com/coins/images/14146/thumb/agve.png?1614659384","dexguru":{"address":"0x848e0ba28b637e8490d88bae51fa99c87116409b","volume_24h":0,"liquidity":0,"volume_24h_usd":0,"liquidity_usd":0,"price_usd":0,"volume_24h_delta":0,"liquidity_24h_delta":0,"price_24h_delta":0,"volume_24h_delta_usd":0,"liquidity_24h_delta_usd":0,"price_24h_delta_usd":0,"timestamp":1642082923},"issue":"Inconsitent Liquidity"},{"chainId":42161,"address":"0x82af49447d8a07e3bd95bd0d56f35241523fbab1","name":"WETH","symbol":"WETH","decimals":18,"logoURI":"https://assets.coingecko.com/coins/images/2518/thumb/weth.png?1628852295","dexscreener":{"priceUsd":"1429.74","source":"dexscreener","liquidity":2557820},"dexguru":{"address":"0x82af49447d8a07e3bd95bd0d56f35241523fbab1","volume_24h":1706.4900103644159,"liquidity":44337.958081019,"volume_24h_usd":2532008.0778604248,"liquidity_usd":63605553.167858,"price_usd":1430.8380547945262,"volume_24h_delta":0.03808300730968386,"liquidity_24h_delta":0.014314128848963553,"price_24h_delta":0,"volume_24h_delta_usd":-0.0332765123723879,"liquidity_24h_delta_usd":-0.04324387628964953,"price_24h_delta_usd":-0.05343833999851911,"timestamp":1658808480},"paraswap":{"srcToken":"0x82af49447d8a07e3bd95bd0d56f35241523fbab1","network":42161,"destToken":"0xfd086bc7cd5c481dcc9c85ebe478a1c0b69fcbb9","destDecimals":6,"srcDecimals":18,"destAmount":"1430443399","srcAmount":"1000000000000000000","srcUSD":"1435.6900000000","maxImpactReached":false,"priceUsd":"1431.8738423990"}},{"chainId":42161,"address":"0xff970a61a04b1ca14834a43f5de4533ebddb5cc8","name":"USD Coin","symbol":"USDC","decimals":6,"logoURI":"https://assets.coingecko.com/coins/images/6319/thumb/USD_Coin_icon.png?1547042389","dexscreener":null,"dexguru":{"address":"0xff970a61a04b1ca14834a43f5de4533ebddb5cc8","volume_24h":1674.4669326955345,"liquidity":41452.641594281,"volume_24h_usd":2490446.236777392,"liquidity_usd":59490060.095507,"price_usd":1,"volume_24h_delta":0.3149061877213286,"liquidity_24h_delta":0.08638901777444506,"price_24h_delta":0.0632788518711839,"volume_24h_delta_usd":0.23038183851887367,"liquidity_24h_delta_usd":0.02545664229010303,"price_24h_delta_usd":0.0007995550775841819,"timestamp":1658808480},"paraswap":{"srcToken":"0xff970a61a04b1ca14834a43f5de4533ebddb5cc8","network":42161,"destToken":"0xfd086bc7cd5c481dcc9c85ebe478a1c0b69fcbb9","destDecimals":6,"srcDecimals":6,"destAmount":"994431","srcAmount":"1000000","srcUSD":"1.0010000000","maxImpactReached":false,"priceUsd":"0.9954254310"}},{"chainId":42161,"address":"0x3a8b787f78d775aecfeea15706d4221b40f345ab","name":"Celer Network","symbol":"CELR","decimals":18,"logoURI":"https://assets.coingecko.com/coins/images/4379/thumb/Celr.png?1554705437","dexguru":{"address":"0x3a8b787f78d775aecfeea15706d4221b40f345ab","volume_24h":0,"liquidity":0.65094380651455,"volume_24h_usd":0,"liquidity_usd":1002.5531496456,"price_usd":0.022193536707110616,"volume_24h_delta":0,"liquidity_24h_delta":1,"price_24h_delta":1,"volume_24h_delta_usd":0,"liquidity_24h_delta_usd":1,"price_24h_delta_usd":1,"timestamp":1658355240},"issue":"Inconsitent Liquidity"},{"chainId":42161,"address":"0x2f2a2543b76a4166549f7aab2e75bef0aefc5b0f","name":"Wrapped Bitcoin","symbol":"WBTC","decimals":18,"logoURI":"https://assets.coingecko.com/coins/images/7598/thumb/wrapped_bitcoin_wbtc.png?1548822744","dexscreener":{"priceUsd":"21174.12","source":"dexscreener","liquidity":2589418},"dexguru":{"address":"0x2f2a2543b76a4166549f7aab2e75bef0aefc5b0f","volume_24h":453.44235032003434,"liquidity":15712.933269047,"volume_24h_usd":678181.639174011,"liquidity_usd":22465725.72013,"price_usd":21067.249334088086,"volume_24h_delta":-0.21153468349873347,"liquidity_24h_delta":0.03173761077760589,"price_24h_delta":0.02072659831382963,"volume_24h_delta_usd":-0.2616981384837699,"liquidity_24h_delta_usd":-0.027241301909322044,"price_24h_delta_usd":-0.03757188630135194,"timestamp":1658808240},"paraswap":{"srcToken":"0x2f2a2543b76a4166549f7aab2e75bef0aefc5b0f","network":42161,"destToken":"0xfd086bc7cd5c481dcc9c85ebe478a1c0b69fcbb9","destDecimals":6,"srcDecimals":8,"destAmount":"209649280000000000000","srcAmount":"1000000000000000000","srcUSD":"211730000000000.0000000000","maxImpactReached":false,"priceUsd":"209858929280000.0000000000"}},{"chainId":42161,"address":"0x23a941036ae778ac51ab04cea08ed6e2fe103614","name":"The Graph","symbol":"GRT","decimals":18,"logoURI":"https://assets.coingecko.com/coins/images/13397/thumb/Graph_Token.png?1608145566","dexguru":{"address":"0x23a941036ae778ac51ab04cea08ed6e2fe103614","volume_24h":0.0051588863244682375,"liquidity":0.74210436953712,"volume_24h_usd":8.344359139223622,"liquidity_usd":1122.3348769736,"price_usd":0.1091846774356212,"volume_24h_delta":1,"liquidity_24h_delta":-0.006732966689680469,"price_24h_delta":-0.013437248393935716,"volume_24h_delta_usd":1,"liquidity_24h_delta_usd":0.033882128473586764,"price_24h_delta_usd":0.02690370594893941,"timestamp":1658759040},"issue":"Inconsitent Liquidity"},{"chainId":42161,"address":"0x0e15258734300290a651fdbae8deb039a8e7a2fa","name":"AlchemyDAO","symbol":"ALCH","decimals":18,"logoURI":"https://assets.coingecko.com/coins/images/14719/thumb/sbEW5W8.png?1617939648","dexguru":{"address":"0x0e15258734300290a651fdbae8deb039a8e7a2fa","volume_24h":0,"liquidity":0.01828439838902,"volume_24h_usd":0,"liquidity_usd":53.6406153919,"price_usd":0.07891871451266916,"volume_24h_delta":-1,"liquidity_24h_delta":0,"price_24h_delta":0,"volume_24h_delta_usd":-1,"liquidity_24h_delta_usd":0,"price_24h_delta_usd":0,"timestamp":1637219106},"issue":"Inconsitent Liquidity"},{"chainId":42161,"address":"0x11cdb42b0eb46d95f990bedd4695a6e3fa034978","name":"Curve DAO","symbol":"CRV","decimals":18,"logoURI":"https://assets.coingecko.com/coins/images/12124/thumb/Curve.png?1597369484","dexscreener":{"priceUsd":"1.17","source":"dexscreener","liquidity":134478},"dexguru":{"address":"0x11cdb42b0eb46d95f990bedd4695a6e3fa034978","volume_24h":20.176029591822505,"liquidity":59.788323264906,"volume_24h_usd":30379.75296596706,"liquidity_usd":85403.717953427,"price_usd":1.1667285128064357,"volume_24h_delta":0.004339810213001969,"liquidity_24h_delta":-0.05537678226475631,"price_24h_delta":-0.04662125622787688,"volume_24h_delta_usd":-0.03838308948019788,"liquidity_24h_delta_usd":-0.10004150504928676,"price_24h_delta_usd":-0.09135153854056281,"timestamp":1658807340},"paraswap":{"srcToken":"0x11cdb42b0eb46d95f990bedd4695a6e3fa034978","network":42161,"destToken":"0xfd086bc7cd5c481dcc9c85ebe478a1c0b69fcbb9","destDecimals":6,"srcDecimals":18,"destAmount":"1284768","srcAmount":"1000000000000000000","srcUSD":"1.1800000000","maxImpactReached":false,"priceUsd":"1.2860527680"}},{"chainId":42161,"address":"0x4e352cf164e64adcbad318c3a1e222e9eba4ce42","name":"MCDEX","symbol":"MCB","decimals":18,"logoURI":"https://assets.coingecko.com/coins/images/11796/thumb/mcb.png?1594355515","dexscreener":{"priceUsd":"2.39","source":"dexscreener","liquidity":550069},"dexguru":{"address":"0x4e352cf164e64adcbad318c3a1e222e9eba4ce42","volume_24h":0.1481018175578341,"liquidity":7.0352415044984,"volume_24h_usd":222.94723230698912,"liquidity_usd":10075.92761476,"price_usd":2.368590560908297,"volume_24h_delta":1.7161300497912542,"liquidity_24h_delta":0.02067593009333834,"price_24h_delta":0.04163449325094883,"volume_24h_delta_usd":1.5358770380918567,"liquidity_24h_delta_usd":-0.06285411481864735,"price_24h_delta_usd":-0.04361075789858646,"timestamp":1658794980},"paraswap":{"srcToken":"0x4e352cf164e64adcbad318c3a1e222e9eba4ce42","network":42161,"destToken":"0xfd086bc7cd5c481dcc9c85ebe478a1c0b69fcbb9","destDecimals":6,"srcDecimals":18,"destAmount":"2386190","srcAmount":"1000000000000000000","srcUSD":"2.4100000000","maxImpactReached":false,"priceUsd":"2.3885761900"}},{"chainId":42161,"address":"0xf97f4df75117a78c1a5a0dbb814af92458539fb4","name":"Chainlink","symbol":"LINK","decimals":18,"logoURI":"https://assets.coingecko.com/coins/images/877/thumb/chainlink-new-logo.png?1547034700","dexscreener":{"priceUsd":"6.26","source":"dexscreener","liquidity":177833},"dexguru":{"address":"0xf97f4df75117a78c1a5a0dbb814af92458539fb4","volume_24h":13.025319993834739,"liquidity":90.147691448229,"volume_24h_usd":19452.443786476724,"liquidity_usd":129570.16631324,"price_usd":6.244161085640084,"volume_24h_delta":0.22347315066164727,"liquidity_24h_delta":0.005745739721329134,"price_24h_delta":0.004892664624754481,"volume_24h_delta_usd":0.1410126630096373,"liquidity_24h_delta_usd":-0.0500287932819639,"price_24h_delta_usd":-0.05990792242810772,"timestamp":1658803980},"paraswap":{"srcToken":"0xf97f4df75117a78c1a5a0dbb814af92458539fb4","network":42161,"destToken":"0xfd086bc7cd5c481dcc9c85ebe478a1c0b69fcbb9","destDecimals":6,"srcDecimals":18,"destAmount":"6378324","srcAmount":"1000000000000000000","srcUSD":"6.3900000000","maxImpactReached":false,"priceUsd":"6.3847023240"}},{"chainId":42161,"address":"0x031d35296154279dc1984dcd93e392b1f946737b","name":"Cap","symbol":"CAP","decimals":18,"logoURI":"https://assets.coingecko.com/coins/images/11775/thumb/CAP.png?1594083244","dexguru":{"address":"0x031d35296154279dc1984dcd93e392b1f946737b","volume_24h":4.829211157298322,"liquidity":3.4426268136483,"volume_24h_usd":7489.888511479592,"liquidity_usd":5061.3508777554,"price_usd":65.37857156805568,"volume_24h_delta":4.061085220048346,"liquidity_24h_delta":-0.04629509497840368,"price_24h_delta":-0.09676884255575308,"volume_24h_delta_usd":4.086210384635063,"liquidity_24h_delta_usd":-0.12660510861524876,"price_24h_delta_usd":-0.17282854004668405,"timestamp":1658778360},"issue":"Inconsitent Liquidity"},{"chainId":42161,"address":"0xfa7f8980b0f1e64a2062791cc3b0871572f1f7f0","name":"Uniswap","symbol":"UNI","decimals":18,"logoURI":"https://assets.coingecko.com/coins/images/12504/thumb/uniswap-uni.png?1600306604","dexscreener":{"priceUsd":"6.85","source":"dexscreener","liquidity":235760},"dexguru":{"address":"0xfa7f8980b0f1e64a2062791cc3b0871572f1f7f0","volume_24h":49.083116435129796,"liquidity":67.716066153874,"volume_24h_usd":73488.1294571838,"liquidity_usd":96993.567198298,"price_usd":6.867444692203857,"volume_24h_delta":0.02322868673668854,"liquidity_24h_delta":0.10015677615585473,"price_24h_delta":0.04640037844289399,"volume_24h_delta_usd":-0.032534569779016795,"liquidity_24h_delta_usd":0.029371001738010518,"price_24h_delta_usd":-0.02027675285422083,"timestamp":1658807760},"paraswap":{"srcToken":"0xfa7f8980b0f1e64a2062791cc3b0871572f1f7f0","network":42161,"destToken":"0xfd086bc7cd5c481dcc9c85ebe478a1c0b69fcbb9","destDecimals":6,"srcDecimals":18,"destAmount":"6796966","srcAmount":"1000000000000000000","srcUSD":"6.8400000000","maxImpactReached":false,"priceUsd":"6.8037629660"}},{"chainId":42161,"address":"0x3e6648c5a70a150a88bce65f4ad4d506fe15d2af","name":"Spell","symbol":"SPELL","decimals":18,"logoURI":"https://assets.coingecko.com/coins/images/15861/thumb/abracadabra-3.png?1622544862","dexscreener":{"priceUsd":"0.0009401","source":"dexscreener","liquidity":740571.1954314294},"dexguru":{"address":"0x3e6648c5a70a150a88bce65f4ad4d506fe15d2af","volume_24h":2.2812529474776153,"liquidity":259.55147462523,"volume_24h_usd":3414.3325261293185,"liquidity_usd":370071.09524903,"price_usd":0.0009395429798214475,"volume_24h_delta":-0.6723507477181541,"liquidity_24h_delta":0.0010414582795885612,"price_24h_delta":0.001517866979359028,"volume_24h_delta_usd":-0.6904675253589511,"liquidity_24h_delta_usd":-0.0607826746261696,"price_24h_delta_usd":-0.06051067407498837,"timestamp":1658806740},"paraswap":null},{"chainId":42161,"address":"0x82e3a8f066a6989666b031d916c43672085b1582","name":"yearn finance","symbol":"YFI","decimals":18,"logoURI":"https://assets.coingecko.com/coins/images/11849/thumb/yfi-192x192.png?1598325330","dexguru":{"address":"0x82e3a8f066a6989666b031d916c43672085b1582","volume_24h":0,"liquidity":1.0701876479511,"volume_24h_usd":0,"liquidity_usd":3553.9107122235,"price_usd":22820.238918304924,"volume_24h_delta":0,"liquidity_24h_delta":0,"price_24h_delta":0,"volume_24h_delta_usd":0,"liquidity_24h_delta_usd":0,"price_24h_delta_usd":0,"timestamp":1635050583},"issue":"Inconsitent Liquidity"},{"chainId":42161,"address":"0x965772e0e9c84b6f359c8597c891108dcf1c5b1a","name":"Pickle Finance","symbol":"PICKLE","decimals":18,"logoURI":"https://assets.coingecko.com/coins/images/12435/thumb/0M4W6Yr6_400x400.jpg?1643006080","dexguru":{"address":"0x965772e0e9c84b6f359c8597c891108dcf1c5b1a","volume_24h":0,"liquidity":0,"volume_24h_usd":0,"liquidity_usd":0,"price_usd":0,"volume_24h_delta":0,"liquidity_24h_delta":0,"price_24h_delta":0,"volume_24h_delta_usd":0,"liquidity_24h_delta_usd":0,"price_24h_delta_usd":0,"timestamp":1650913847},"issue":"Inconsitent Liquidity"},{"chainId":42161,"address":"0x040d1edc9569d4bab2d15287dc5a4f10f56a56b8","name":"Balancer","symbol":"BAL","decimals":18,"logoURI":"https://assets.coingecko.com/coins/images/11683/thumb/Balancer.png?1592792958","dexguru":{"address":"0x040d1edc9569d4bab2d15287dc5a4f10f56a56b8","volume_24h":0,"liquidity":0.0010101238301855,"volume_24h_usd":0,"liquidity_usd":2.8468011800871,"price_usd":0.45132508453096365,"volume_24h_delta":-1,"liquidity_24h_delta":0,"price_24h_delta":0,"volume_24h_delta_usd":-1,"liquidity_24h_delta_usd":0,"price_24h_delta_usd":0,"timestamp":1637077133},"issue":"Inconsitent Liquidity"},{"chainId":42161,"address":"0x354a6da3fcde098f8389cad84b0182725c6c91de","name":"Compound","symbol":"COMP","decimals":18,"logoURI":"https://assets.coingecko.com/coins/images/10775/thumb/COMP.png?1592625425","dexguru":{"address":"0x354a6da3fcde098f8389cad84b0182725c6c91de","volume_24h":0,"liquidity":3.6540983436747,"volume_24h_usd":0,"liquidity_usd":5349.0441956175,"price_usd":44.07941054850721,"volume_24h_delta":-1,"liquidity_24h_delta":0,"price_24h_delta":0,"volume_24h_delta_usd":-1,"liquidity_24h_delta_usd":0,"price_24h_delta_usd":0,"timestamp":1655005260},"issue":"Inconsitent Liquidity"},{"chainId":42161,"address":"0xb965029343d55189c25a7f3e0c9394dc0f5d41b1","name":"Indexed Finance","symbol":"NDX","decimals":18,"logoURI":"https://assets.coingecko.com/coins/images/13546/thumb/indexed-light.74bb5471.png?1609712728","dexguru":{"address":"0xb965029343d55189c25a7f3e0c9394dc0f5d41b1","volume_24h":0,"liquidity":0,"volume_24h_usd":0,"liquidity_usd":0,"price_usd":0,"volume_24h_delta":0,"liquidity_24h_delta":0,"price_24h_delta":0,"volume_24h_delta_usd":0,"liquidity_24h_delta_usd":0,"price_24h_delta_usd":0,"timestamp":1650913655},"issue":"Inconsitent Liquidity"},{"chainId":42161,"address":"0x10010078a54396f62c96df8532dc2b4847d47ed3","name":"Hundred Finance","symbol":"HND","decimals":18,"logoURI":"https://assets.coingecko.com/coins/images/18445/thumb/hnd.PNG?1632054703","dexguru":{"address":"0x10010078a54396f62c96df8532dc2b4847d47ed3","volume_24h":0,"liquidity":0,"volume_24h_usd":0,"liquidity_usd":0,"price_usd":0.828943624997499,"volume_24h_delta":0,"liquidity_24h_delta":0,"price_24h_delta":1,"volume_24h_delta_usd":0,"liquidity_24h_delta_usd":0,"price_24h_delta_usd":1,"timestamp":1639185453},"issue":"Inconsitent Liquidity"},{"chainId":42161,"address":"0xea986d33ef8a20a96120ecc44dbdd49830192043","name":"Auctus","symbol":"AUC","decimals":18,"logoURI":"https://assets.coingecko.com/coins/images/2165/thumb/Auc_Discord_Avatar1.png?1618983355","dexguru":{"address":"0xea986d33ef8a20a96120ecc44dbdd49830192043","volume_24h":0,"liquidity":0,"volume_24h_usd":0,"liquidity_usd":0,"price_usd":0,"volume_24h_delta":0,"liquidity_24h_delta":0,"price_24h_delta":0,"volume_24h_delta_usd":0,"liquidity_24h_delta_usd":0,"price_24h_delta_usd":0,"timestamp":1650913669},"issue":"Inconsitent Liquidity"},{"chainId":42161,"address":"0xbfa641051ba0a0ad1b0acf549a89536a0d76472e","name":"Badger DAO","symbol":"BADGER","decimals":18,"logoURI":"https://assets.coingecko.com/coins/images/13287/thumb/badger_dao_logo.jpg?1607054976","dexscreener":{"priceUsd":"3.59","source":"dexscreener","liquidity":332046.84943350294},"dexguru":{"address":"0xbfa641051ba0a0ad1b0acf549a89536a0d76472e","volume_24h":4.65439554177599,"liquidity":116.92517854665,"volume_24h_usd":7036.945643086921,"liquidity_usd":166023.42478725,"price_usd":3.6074526235592255,"volume_24h_delta":-0.04230938622185145,"liquidity_24h_delta":0.04689745814924232,"price_24h_delta":0.0958662892042607,"volume_24h_delta_usd":-0.09718630306947858,"liquidity_24h_delta_usd":0.014284613789386929,"price_24h_delta_usd":0.061727972742683185,"timestamp":1658801760},"paraswap":null},{"chainId":42161,"address":"0x04cb2d263a7489f02d813eaab9ba1bb8466347f2","name":"Chemix Ecology Governance","symbol":"KUN","decimals":18,"logoURI":"https://assets.coingecko.com/coins/images/13177/thumb/kun_logo.png?1605923919","dexguru":null,"issue":"Inconsitent Liquidity"},{"chainId":42161,"address":"0x69eb4fa4a2fbd498c257c57ea8b7655a2559a581","name":"DODO","symbol":"DODO","decimals":18,"logoURI":"https://assets.coingecko.com/coins/images/12651/thumb/dodo_logo.png?1601433025","dexguru":{"address":"0x69eb4fa4a2fbd498c257c57ea8b7655a2559a581","volume_24h":0,"liquidity":0,"volume_24h_usd":0,"liquidity_usd":0,"price_usd":0.734484804512955,"volume_24h_delta":0,"liquidity_24h_delta":0,"price_24h_delta":1,"volume_24h_delta_usd":0,"liquidity_24h_delta_usd":0,"price_24h_delta_usd":1,"timestamp":1635148765},"issue":"Inconsitent Liquidity"},{"chainId":42161,"address":"0xa0b862f60edef4452f25b4160f177db44deb6cf1","name":"Gnosis","symbol":"GNO","decimals":18,"logoURI":"https://assets.coingecko.com/coins/images/662/thumb/logo_square_simple_300px.png?1609402668","dexguru":{"address":"0xa0b862f60edef4452f25b4160f177db44deb6cf1","volume_24h":0,"liquidity":0,"volume_24h_usd":0,"liquidity_usd":0,"price_usd":414.8372280129223,"volume_24h_delta":0,"liquidity_24h_delta":0,"price_24h_delta":0,"volume_24h_delta_usd":0,"liquidity_24h_delta_usd":0,"price_24h_delta_usd":0,"timestamp":1636702823},"issue":"Inconsitent Liquidity"},{"chainId":42161,"address":"0xc3ae0333f0f34aa734d5493276223d95b8f9cb37","name":"DXdao","symbol":"DXD","decimals":18,"logoURI":"https://assets.coingecko.com/coins/images/11148/thumb/dxdao.png?1607999331","dexscreener":{"priceUsd":"504.47","source":"dexscreener","liquidity":335895.4786261781},"dexguru":{"address":"0xc3ae0333f0f34aa734d5493276223d95b8f9cb37","volume_24h":7.991862105875467,"liquidity":109.09185846439,"volume_24h_usd":12730.067735597862,"liquidity_usd":167947.73939991,"price_usd":507.8709275125477,"volume_24h_delta":3.8466526834985713,"liquidity_24h_delta":-0.008906603743169884,"price_24h_delta":-0.017920395930090885,"volume_24h_delta_usd":3.8087248653971395,"liquidity_24h_delta_usd":-0.04634673130795078,"price_24h_delta_usd":-0.05502001317504732,"timestamp":1658754360},"paraswap":null},{"chainId":42161,"address":"0xf4d48ce3ee1ac3651998971541badbb9a14d7234","name":"Cream","symbol":"CREAM","decimals":18,"logoURI":"https://assets.coingecko.com/coins/images/11976/thumb/Cream.png?1596593418","dexguru":null,"issue":"Inconsitent Liquidity"},{"chainId":42161,"address":"0xd4d42f0b6def4ce0383636770ef773390d85c61a","name":"Sushi","symbol":"SUSHI","decimals":18,"logoURI":"https://assets.coingecko.com/coins/images/12271/thumb/512x512_Logo_no_chop.png?1606986688","dexscreener":{"priceUsd":"1.35","source":"dexscreener","liquidity":283283.4863889608},"dexguru":{"address":"0xd4d42f0b6def4ce0383636770ef773390d85c61a","volume_24h":20.25520677764827,"liquidity":98.713529181325,"volume_24h_usd":30101.9450374879,"liquidity_usd":141641.7432587,"price_usd":1.3544541423247578,"volume_24h_delta":0.9751563289696092,"liquidity_24h_delta":0.059157830473566236,"price_24h_delta":0.12040719881088624,"volume_24h_delta_usd":0.8498246155513863,"liquidity_24h_delta_usd":0.00007222133660967026,"price_24h_delta_usd":0.05790476535051307,"timestamp":1658808480},"paraswap":{"srcToken":"0xd4d42f0b6def4ce0383636770ef773390d85c61a","network":42161,"destToken":"0xfd086bc7cd5c481dcc9c85ebe478a1c0b69fcbb9","destDecimals":6,"srcDecimals":18,"destAmount":"1348462","srcAmount":"1000000000000000000","srcUSD":"1.3500000000","maxImpactReached":false,"priceUsd":"1.3498104620"}},{"chainId":42161,"address":"0xda10009cbd5d07dd0cecc66161fc93d7c9000da1","name":"Dai","symbol":"DAI","decimals":18,"logoURI":"https://assets.coingecko.com/coins/images/9956/thumb/4943.png?1636636734","dexscreener":{"priceUsd":"1.00","source":"dexscreener","liquidity":3165971},"dexguru":{"address":"0xda10009cbd5d07dd0cecc66161fc93d7c9000da1","volume_24h":322.2085266595358,"liquidity":1713.9145992723,"volume_24h_usd":470360.7572729018,"liquidity_usd":2454345.2504537,"price_usd":0.9997482302480206,"volume_24h_delta":-0.07264791495693683,"liquidity_24h_delta":0.019148323198007983,"price_24h_delta":0.05444685556381481,"volume_24h_delta_usd":-0.14753655769412452,"liquidity_24h_delta_usd":-0.03299288190998786,"price_24h_delta_usd":-0.005385769416893378,"timestamp":1658808060},"paraswap":{"srcToken":"0xda10009cbd5d07dd0cecc66161fc93d7c9000da1","network":42161,"destToken":"0xfd086bc7cd5c481dcc9c85ebe478a1c0b69fcbb9","destDecimals":6,"srcDecimals":18,"destAmount":"972166","srcAmount":"1000000000000000000","srcUSD":"1.0010000000","maxImpactReached":false,"priceUsd":"0.9731381660"}},{"chainId":42161,"address":"0x51fc0f6660482ea73330e414efd7808811a57fa2","name":"Premia","symbol":"PREMIA","decimals":18,"logoURI":"https://assets.coingecko.com/coins/images/13962/thumb/apple-touch-icon.png?1623679482","dexscreener":{"priceUsd":"0.7424","source":"dexscreener","liquidity":320742.0171617891},"dexguru":{"address":"0x51fc0f6660482ea73330e414efd7808811a57fa2","volume_24h":5.044512989117942,"liquidity":109.38688162759,"volume_24h_usd":8108.39349245882,"liquidity_usd":160479.0031693,"price_usd":0.7379113387686262,"volume_24h_delta":11.075326426282853,"liquidity_24h_delta":0.0022682764314334515,"price_24h_delta":0.004403558102352618,"volume_24h_delta_usd":11.11753897900918,"liquidity_24h_delta_usd":-0.04481092959292397,"price_24h_delta_usd":-0.042775947779909826,"timestamp":1658777820},"paraswap":{"srcToken":"0x51fc0f6660482ea73330e414efd7808811a57fa2","network":42161,"destToken":"0xfd086bc7cd5c481dcc9c85ebe478a1c0b69fcbb9","destDecimals":6,"srcDecimals":18,"destAmount":"718527","srcAmount":"1000000000000000000","srcUSD":"0.7329600000","maxImpactReached":false,"priceUsd":"0.7192455270"}},{"chainId":42161,"address":"0xef888bca6ab6b1d26dbec977c455388ecd794794","name":"Rari Governance","symbol":"RGT","decimals":18,"logoURI":"https://assets.coingecko.com/coins/images/12900/thumb/Rari_Logo_Transparent.png?1613978014","dexguru":{"address":"0xef888bca6ab6b1d26dbec977c455388ecd794794","volume_24h":0,"liquidity":9.992453145790988e-56,"volume_24h_usd":0,"liquidity_usd":3.787265497432292e-52,"price_usd":1.1139016168918508e-35,"volume_24h_delta":0,"liquidity_24h_delta":0,"price_24h_delta":0,"volume_24h_delta_usd":0,"liquidity_24h_delta_usd":0,"price_24h_delta_usd":0,"timestamp":1637011520},"issue":"Inconsitent Liquidity"},{"chainId":42161,"address":"0x3509f19581afedeff07c53592bc0ca84e4855475","name":"xDollar Stablecoin","symbol":"XUSD","decimals":18,"logoURI":"https://assets.coingecko.com/coins/images/16291/thumb/xUSD-web-transparent.png?1623661715","dexguru":{"address":"0x3509f19581afedeff07c53592bc0ca84e4855475","volume_24h":0,"liquidity":0,"volume_24h_usd":0,"liquidity_usd":0,"price_usd":0.9749623099108936,"volume_24h_delta":0,"liquidity_24h_delta":0,"price_24h_delta":0,"volume_24h_delta_usd":0,"liquidity_24h_delta_usd":0,"price_24h_delta_usd":0,"timestamp":1636057722},"issue":"Inconsitent Liquidity"},{"chainId":42161,"address":"0x5837d843d49ffdefc78fe09b5f371427c917946f","name":"QIAN Second Generation Dollar","symbol":"QSD","decimals":18,"logoURI":"https://assets.coingecko.com/coins/images/17985/thumb/QSD_.png?1630029729","dexguru":null,"issue":"Inconsitent Liquidity"},{"chainId":42161,"address":"0x155f0dd04424939368972f4e1838687d6a831151","name":"ArbiDoge","symbol":"ADOGE","decimals":18,"logoURI":"https://assets.coingecko.com/coins/images/18333/thumb/Screen-Shot-2021-09-04-at-11-59-16-AM.png?1631584395","dexscreener":{"priceUsd":"0.0000000116","source":"dexscreener","liquidity":40397.00113466196},"dexguru":{"address":"0x155f0dd04424939368972f4e1838687d6a831151","volume_24h":0,"liquidity":13.22942054649,"volume_24h_usd":0,"liquidity_usd":20107.985155948,"price_usd":1.1518645513421298e-8,"volume_24h_delta":-1,"liquidity_24h_delta":0,"price_24h_delta":0,"volume_24h_delta_usd":-1,"liquidity_24h_delta_usd":0,"price_24h_delta_usd":0,"timestamp":1658765820},"paraswap":null},{"chainId":42161,"address":"0x995c235521820f2637303ca1970c7c044583df44","name":"Visor","symbol":"VISR","decimals":18,"logoURI":"https://assets.coingecko.com/coins/images/14381/thumb/visor_logo.png?1615782828","dexguru":{"address":"0x995c235521820f2637303ca1970c7c044583df44","volume_24h":0,"liquidity":0.027977822706894,"volume_24h_usd":0,"liquidity_usd":84.717550157987,"price_usd":0.0009596263765896422,"volume_24h_delta":0,"liquidity_24h_delta":0,"price_24h_delta":0,"volume_24h_delta_usd":0,"liquidity_24h_delta_usd":0,"price_24h_delta_usd":0,"timestamp":1637263312},"issue":"Inconsitent Liquidity"},{"chainId":42161,"address":"0xcafcd85d8ca7ad1e1c6f82f651fa15e33aefd07b","name":"WOO Network","symbol":"WOO","decimals":18,"logoURI":"https://assets.coingecko.com/coins/images/12921/thumb/w2UiemF__400x400.jpg?1603670367","dexguru":null,"issue":"Inconsitent Liquidity"},{"chainId":42161,"address":"0xa970af1a584579b618be4d69ad6f73459d112f95","name":"sUSD","symbol":"SUSD","decimals":18,"logoURI":"https://assets.coingecko.com/coins/images/5013/thumb/sUSD.png?1616150765","dexguru":{"address":"0xa970af1a584579b618be4d69ad6f73459d112f95","volume_24h":0,"liquidity":0,"volume_24h_usd":0,"liquidity_usd":0,"price_usd":0,"volume_24h_delta":0,"liquidity_24h_delta":0,"price_24h_delta":0,"volume_24h_delta_usd":0,"liquidity_24h_delta_usd":0,"price_24h_delta_usd":0,"timestamp":1650913994},"issue":"Inconsitent Liquidity"},{"chainId":42161,"address":"0xa72159fc390f0e3c6d415e658264c7c4051e9b87","name":"Tracer DAO","symbol":"TCR","decimals":18,"logoURI":"https://assets.coingecko.com/coins/images/18271/thumb/tracer_logo.png?1631176676","dexscreener":{"priceUsd":"0.0344","source":"dexscreener","liquidity":67665},"dexguru":{"address":"0xa72159fc390f0e3c6d415e658264c7c4051e9b87","volume_24h":5.227253781276378,"liquidity":29.222289496474,"volume_24h_usd":7791.746421246402,"liquidity_usd":42993.371851257,"price_usd":0.03456075483154127,"volume_24h_delta":1.9749858805058564,"liquidity_24h_delta":0.06681682032333933,"price_24h_delta":-0.04563738298345018,"volume_24h_delta_usd":1.7842377419897049,"liquidity_24h_delta_usd":-0.02717647001632622,"price_24h_delta_usd":-0.1275579131338431,"timestamp":1658799240},"paraswap":{"srcToken":"0xa72159fc390f0e3c6d415e658264c7c4051e9b87","network":42161,"destToken":"0xfd086bc7cd5c481dcc9c85ebe478a1c0b69fcbb9","destDecimals":6,"srcDecimals":18,"destAmount":"30866","srcAmount":"1000000000000000000","srcUSD":"0.0351419600","maxImpactReached":false,"priceUsd":"0.0308968660"}},{"chainId":42161,"address":"0xde903e2712288a1da82942dddf2c20529565ac30","name":"Swapr","symbol":"SWPR","decimals":18,"logoURI":"https://assets.coingecko.com/coins/images/18740/thumb/swapr.jpg?1633516501","dexscreener":{"priceUsd":"0.01666","source":"dexscreener","liquidity":70936.47421288119},"dexguru":{"address":"0xde903e2712288a1da82942dddf2c20529565ac30","volume_24h":0.5363522101381344,"liquidity":24.925188133642,"volume_24h_usd":784.798872650802,"liquidity_usd":35336.915422408,"price_usd":0.01657287023476253,"volume_24h_delta":0.6278639031183838,"liquidity_24h_delta":-0.002262207561514338,"price_24h_delta":-0.0018796372225783186,"volume_24h_delta_usd":0.538930300752678,"liquidity_24h_delta_usd":-0.07866048660311245,"price_24h_delta_usd":-0.07830721024874765,"timestamp":1658804160},"paraswap":{"srcToken":"0xde903e2712288a1da82942dddf2c20529565ac30","network":42161,"destToken":"0xfd086bc7cd5c481dcc9c85ebe478a1c0b69fcbb9","destDecimals":6,"srcDecimals":18,"destAmount":"18217","srcAmount":"1000000000000000000","srcUSD":"0.0169424300","maxImpactReached":false,"priceUsd":"0.0182352170"}},{"chainId":42161,"address":"0x7ba4a00d54a07461d9db2aef539e91409943adc9","name":"Stake DAO","symbol":"SDT","decimals":18,"logoURI":"https://assets.coingecko.com/coins/images/13724/thumb/stakedao_logo.jpg?1611195011","dexguru":{"address":"0x7ba4a00d54a07461d9db2aef539e91409943adc9","volume_24h":0,"liquidity":0,"volume_24h_usd":0,"liquidity_usd":0,"price_usd":0,"volume_24h_delta":0,"liquidity_24h_delta":0,"price_24h_delta":0,"volume_24h_delta_usd":0,"liquidity_24h_delta_usd":0,"price_24h_delta_usd":0,"timestamp":1643335908},"issue":"Inconsitent Liquidity"},{"chainId":42161,"address":"0x2e9a6df78e42a30712c10a9dc4b1c8656f8f2879","name":"Maker","symbol":"MKR","decimals":18,"logoURI":"https://assets.coingecko.com/coins/images/1364/thumb/Mark_Maker.png?1585191826","dexguru":null,"issue":"Inconsitent Liquidity"},{"chainId":42161,"address":"0x99f40b01ba9c469193b360f72740e416b17ac332","name":"MATH","symbol":"MATH","decimals":18,"logoURI":"https://assets.coingecko.com/coins/images/11335/thumb/2020-05-19-token-200.png?1589940590","dexguru":{"address":"0x99f40b01ba9c469193b360f72740e416b17ac332","volume_24h":0.06436284591970207,"liquidity":1.2609181295872,"volume_24h_usd":103.23555932781095,"liquidity_usd":2023.1630456939,"price_usd":0.19511873626021384,"volume_24h_delta":-0.5100098400724972,"liquidity_24h_delta":-0.04500918077368434,"price_24h_delta":-0.03947834199143691,"volume_24h_delta_usd":-0.502170757359531,"liquidity_24h_delta_usd":-0.029394944948406297,"price_24h_delta_usd":-0.023773676164796673,"timestamp":1658656380},"issue":"Inconsitent Liquidity"},{"chainId":42161,"address":"0x46d0ce7de6247b0a95f67b43b589b4041bae7fbe","name":"Loopring","symbol":"LRC","decimals":18,"logoURI":"https://assets.coingecko.com/coins/images/913/thumb/LRC.png?1572852344","dexguru":{"address":"0x46d0ce7de6247b0a95f67b43b589b4041bae7fbe","volume_24h":0,"liquidity":0.042050279139132,"volume_24h_usd":0,"liquidity_usd":111.83189864454,"price_usd":1.8221248868612194,"volume_24h_delta":-1,"liquidity_24h_delta":0,"price_24h_delta":0,"volume_24h_delta_usd":-1,"liquidity_24h_delta_usd":0,"price_24h_delta_usd":0,"timestamp":1636768536},"issue":"Inconsitent Liquidity"},{"chainId":42161,"address":"0x7cb16cb78ea464ad35c8a50abf95dff3c9e09d5d","name":"0xBitcoin","symbol":"0XBTC","decimals":8,"logoURI":"https://assets.coingecko.com/coins/images/4454/thumb/0xbtc.png?1561603765","dexguru":{"address":"0x7cb16cb78ea464ad35c8a50abf95dff3c9e09d5d","volume_24h":0,"liquidity":2.9644347698688,"volume_24h_usd":0,"liquidity_usd":8021.1867206533,"price_usd":1.5929168133266343,"volume_24h_delta":-1,"liquidity_24h_delta":0,"price_24h_delta":0,"volume_24h_delta_usd":-1,"liquidity_24h_delta_usd":0,"price_24h_delta_usd":0,"timestamp":1636562732},"issue":"Inconsitent Liquidity"},{"chainId":42161,"address":"0x9c67ee39e3c4954396b9142010653f17257dd39c","name":"Impermax","symbol":"IMX","decimals":18,"logoURI":"https://assets.coingecko.com/coins/images/15126/thumb/Copy_of_200px.png?1619761475","dexguru":{"address":"0x9c67ee39e3c4954396b9142010653f17257dd39c","volume_24h":0.14798876792769025,"liquidity":2.0444173777604,"volume_24h_usd":225.06607964843693,"liquidity_usd":3210.3017069789,"price_usd":0.0006073527631212691,"volume_24h_delta":13.010669594957676,"liquidity_24h_delta":-0.05208828828558479,"price_24h_delta":-0.10165688101610366,"volume_24h_delta_usd":13.69354732975576,"liquidity_24h_delta_usd":0.00818015850429555,"price_24h_delta_usd":-0.04454001686465299,"timestamp":1658272200},"issue":"Inconsitent Liquidity"},{"chainId":42161,"address":"0xa7aa2921618e3d63da433829d448b58c9445a4c3","name":"Rhino fi","symbol":"DVF","decimals":18,"logoURI":"https://assets.coingecko.com/coins/images/16414/thumb/rhinofii.jpg?1657812510","dexscreener":null,"dexguru":{"address":"0xa7aa2921618e3d63da433829d448b58c9445a4c3","volume_24h":0.039093066119996286,"liquidity":8.2161090018799,"volume_24h_usd":61.86284528504054,"liquidity_usd":13415.621290994,"price_usd":1.199926827781001,"volume_24h_delta":-0.8727104635505213,"liquidity_24h_delta":-0.00460800711644898,"price_24h_delta":-0.009208573086090454,"volume_24h_delta_usd":-0.8689850375210112,"liquidity_24h_delta_usd":0.024323177796704797,"price_24h_delta_usd":0.019588895838039293,"timestamp":1658485380},"paraswap":{"srcToken":"0xa7aa2921618e3d63da433829d448b58c9445a4c3","network":42161,"destToken":"0xfd086bc7cd5c481dcc9c85ebe478a1c0b69fcbb9","destDecimals":6,"srcDecimals":18,"destAmount":"1049699","srcAmount":"1000000000000000000","srcUSD":"1.1400000000","maxImpactReached":false,"priceUsd":"1.0507486990"}},{"chainId":42161,"address":"0x4425742f1ec8d98779690b5a3a6276db85ddc01a","name":"The Doge NFT","symbol":"DOG","decimals":18,"logoURI":"https://assets.coingecko.com/coins/images/18111/thumb/Doge.png?1630696110","dexscreener":null,"dexguru":{"address":"0x4425742f1ec8d98779690b5a3a6276db85ddc01a","volume_24h":0,"liquidity":18.656352903789,"volume_24h_usd":0,"liquidity_usd":28721.251348772,"price_usd":0.0011294765239668388,"volume_24h_delta":0,"liquidity_24h_delta":0,"price_24h_delta":0,"volume_24h_delta_usd":0,"liquidity_24h_delta_usd":0,"price_24h_delta_usd":0,"timestamp":1658274840},"paraswap":{"srcToken":"0x4425742f1ec8d98779690b5a3a6276db85ddc01a","network":42161,"destToken":"0xfd086bc7cd5c481dcc9c85ebe478a1c0b69fcbb9","destDecimals":6,"srcDecimals":18,"destAmount":"1048","srcAmount":"1000000000000000000","srcUSD":"0.0010373500","maxImpactReached":false,"priceUsd":"0.0010490480"}},{"chainId":42161,"address":"0x8038f3c971414fd1fc220ba727f2d4a0fc98cb65","name":"dHEDGE DAO","symbol":"DHT","decimals":18,"logoURI":"https://assets.coingecko.com/coins/images/12508/thumb/dht.png?1600752201","dexguru":{"address":"0x8038f3c971414fd1fc220ba727f2d4a0fc98cb65","volume_24h":0,"liquidity":0,"volume_24h_usd":0,"liquidity_usd":0,"price_usd":0.7619639850908649,"volume_24h_delta":0,"liquidity_24h_delta":0,"price_24h_delta":1,"volume_24h_delta_usd":0,"liquidity_24h_delta_usd":0,"price_24h_delta_usd":1,"timestamp":1637996803},"issue":"Inconsitent Liquidity"},{"chainId":42161,"address":"0xae6e3540e97b0b9ea8797b157b510e133afb6282","name":"DEGEN Index","symbol":"DEGEN","decimals":18,"logoURI":"https://assets.coingecko.com/coins/images/14143/thumb/alpha_logo.png?1614651244","dexguru":{"address":"0xae6e3540e97b0b9ea8797b157b510e133afb6282","volume_24h":0,"liquidity":0.27957731048772,"volume_24h_usd":0,"liquidity_usd":816.24801967412,"price_usd":2.336513195085468,"volume_24h_delta":-1,"liquidity_24h_delta":0,"price_24h_delta":0,"volume_24h_delta_usd":-1,"liquidity_24h_delta_usd":0,"price_24h_delta_usd":0,"timestamp":1635417957},"issue":"Inconsitent Liquidity"},{"chainId":42161,"address":"0xaaa62d9584cbe8e4d68a43ec91bff4ff1fadb202","name":"AntiMatter","symbol":"MATTER","decimals":18,"logoURI":"https://assets.coingecko.com/coins/images/14112/thumb/antimatter_icon.png?1614395992","dexscreener":null,"dexguru":{"address":"0xaaa62d9584cbe8e4d68a43ec91bff4ff1fadb202","volume_24h":0,"liquidity":16.727214611586,"volume_24h_usd":0,"liquidity_usd":38138.025121532,"price_usd":0.2854739473374181,"volume_24h_delta":-1,"liquidity_24h_delta":0,"price_24h_delta":0,"volume_24h_delta_usd":-1,"liquidity_24h_delta_usd":0,"price_24h_delta_usd":0,"timestamp":1635925755},"paraswap":null},{"chainId":42161,"address":"0x32eb7902d4134bf98a28b963d26de779af92a212","name":"Dopex Rebate","symbol":"RDPX","decimals":18,"logoURI":"https://assets.coingecko.com/coins/images/16659/thumb/rDPX_200x200_Coingecko.png?1624614475","dexscreener":{"priceUsd":"18.10","source":"dexscreener","liquidity":7217252.161945326},"dexguru":{"address":"0x32eb7902d4134bf98a28b963d26de779af92a212","volume_24h":198.85912119505562,"liquidity":2715.7440587712,"volume_24h_usd":293813.7538053574,"liquidity_usd":3907227.5205237,"price_usd":18.050423727791916,"volume_24h_delta":0.5444037184893639,"liquidity_24h_delta":-0.02438600899095888,"price_24h_delta":-0.04567716228303794,"volume_24h_delta_usd":0.44237211262496084,"liquidity_24h_delta_usd":-0.07437047132911653,"price_24h_delta_usd":-0.0984381837949381,"timestamp":1658807820},"paraswap":{"srcToken":"0x32eb7902d4134bf98a28b963d26de779af92a212","network":42161,"destToken":"0xfd086bc7cd5c481dcc9c85ebe478a1c0b69fcbb9","destDecimals":6,"srcDecimals":18,"destAmount":"18015349","srcAmount":"1000000000000000000","srcUSD":"18.1300000000","maxImpactReached":false,"priceUsd":"18.0333643490"}},{"chainId":42161,"address":"0x6c2c06790b3e3e3c38e12ee22f8183b37a13ee55","name":"Dopex","symbol":"DPX","decimals":18,"logoURI":"https://assets.coingecko.com/coins/images/16652/thumb/DPX_%281%29.png?1624598630","dexscreener":{"priceUsd":"181.89","source":"dexscreener","liquidity":10569450.181079824},"dexguru":{"address":"0x6c2c06790b3e3e3c38e12ee22f8183b37a13ee55","volume_24h":152.56722696358656,"liquidity":3787.8336839119,"volume_24h_usd":227676.98518713162,"liquidity_usd":5431384.7776535,"price_usd":181.21813286180682,"volume_24h_delta":-0.1765366214001825,"liquidity_24h_delta":-0.04350867270971827,"price_24h_delta":-0.0748288534333841,"volume_24h_delta_usd":-0.21720472249840744,"liquidity_24h_delta_usd":-0.09808825958240065,"price_24h_delta_usd":-0.1290953684781466,"timestamp":1658808000},"paraswap":{"srcToken":"0x6c2c06790b3e3e3c38e12ee22f8183b37a13ee55","network":42161,"destToken":"0xfd086bc7cd5c481dcc9c85ebe478a1c0b69fcbb9","destDecimals":6,"srcDecimals":18,"destAmount":"180992377","srcAmount":"1000000000000000000","srcUSD":"182.1500000000","maxImpactReached":false,"priceUsd":"181.1733693770"}},{"chainId":42161,"address":"0x99c409e5f62e4bd2ac142f17cafb6810b8f0baae","name":"Beefy Finance","symbol":"BIFI","decimals":18,"logoURI":"https://assets.coingecko.com/coins/images/12704/thumb/token.png?1601876182","dexscreener":{"priceUsd":"390.12","source":"dexscreener","liquidity":27059.78546182623},"dexguru":{"address":"0x99c409e5f62e4bd2ac142f17cafb6810b8f0baae","volume_24h":0.2641100166613388,"liquidity":9.5151288815459,"volume_24h_usd":399.0931920106702,"liquidity_usd":13518.24454332,"price_usd":390.17954167185144,"volume_24h_delta":-0.745013283037122,"liquidity_24h_delta":-0.0010321931082029018,"price_24h_delta":-0.0021463563620771403,"volume_24h_delta_usd":-0.7594442569804404,"liquidity_24h_delta_usd":-0.05562683788803172,"price_24h_delta_usd":-0.05668011094444776,"timestamp":1658797620},"paraswap":{"srcToken":"0x99c409e5f62e4bd2ac142f17cafb6810b8f0baae","network":42161,"destToken":"0xfd086bc7cd5c481dcc9c85ebe478a1c0b69fcbb9","destDecimals":6,"srcDecimals":18,"destAmount":"381022021","srcAmount":"1000000000000000000","srcUSD":"399.7300000000","maxImpactReached":false,"priceUsd":"381.4030430210"}},{"chainId":42161,"address":"0x739ca6d71365a08f584c8fc4e1029045fa8abc4b","name":"Wrapped Staked Olympus","symbol":"WSOHM","decimals":18,"logoURI":"https://assets.coingecko.com/coins/images/19221/thumb/token_wsOHM_logo.png?1638764872","dexguru":{"address":"0x739ca6d71365a08f584c8fc4e1029045fa8abc4b","volume_24h":0,"liquidity":0,"volume_24h_usd":0,"liquidity_usd":0,"price_usd":4124.318543802016,"volume_24h_delta":0,"liquidity_24h_delta":0,"price_24h_delta":0,"volume_24h_delta_usd":0,"liquidity_24h_delta_usd":0,"price_24h_delta_usd":0,"timestamp":1637267328},"issue":"Inconsitent Liquidity"},{"chainId":42161,"address":"0x4d15a3a2286d883af0aa1b3f21367843fac63e07","name":"TrueUSD","symbol":"TUSD","decimals":18,"logoURI":"https://assets.coingecko.com/coins/images/3449/thumb/tusd.png?1618395665","dexscreener":{"priceUsd":"1.00","source":"dexscreener","liquidity":1905461},"dexguru":{"address":"0x4d15a3a2286d883af0aa1b3f21367843fac63e07","volume_24h":4.505398210956062,"liquidity":598.14753858325,"volume_24h_usd":6875.105925570181,"liquidity_usd":905361.146087,"price_usd":0.9999068449447909,"volume_24h_delta":141.14160991827308,"liquidity_24h_delta":0.06191225036833006,"price_24h_delta":0.06170613481747738,"volume_24h_delta_usd":133.8733992869313,"liquidity_24h_delta_usd":0.0001959149530113605,"price_24h_delta_usd":0.000001778448894008021,"timestamp":1658781480},"paraswap":{"srcToken":"0x4d15a3a2286d883af0aa1b3f21367843fac63e07","network":42161,"destToken":"0xfd086bc7cd5c481dcc9c85ebe478a1c0b69fcbb9","destDecimals":6,"srcDecimals":18,"destAmount":"1000428","srcAmount":"1000000000000000000","srcUSD":"1.0010000000","maxImpactReached":false,"priceUsd":"1.0014284280"}},{"chainId":42161,"address":"0x17fc002b466eec40dae837fc4be5c67993ddbd6f","name":"Frax","symbol":"FRAX","decimals":18,"logoURI":"https://assets.coingecko.com/coins/images/13422/thumb/frax_logo.png?1608476506","dexscreener":{"priceUsd":"0.9726","source":"dexscreener","liquidity":298.81267},"dexguru":{"address":"0x17fc002b466eec40dae837fc4be5c67993ddbd6f","volume_24h":60.04845898574061,"liquidity":7527.7130942112,"volume_24h_usd":91078.1259027626,"liquidity_usd":10675018.328254,"price_usd":0.998665,"volume_24h_delta":-0.4123498112798725,"liquidity_24h_delta":0.06947881011050455,"price_24h_delta":0.08861216705597942,"volume_24h_delta_usd":-0.43785987752454314,"liquidity_24h_delta_usd":-0.006416502402309235,"price_24h_delta_usd":0.000028038216088556704,"timestamp":1658807160},"paraswap":{"srcToken":"0x17fc002b466eec40dae837fc4be5c67993ddbd6f","network":42161,"destToken":"0xfd086bc7cd5c481dcc9c85ebe478a1c0b69fcbb9","destDecimals":6,"srcDecimals":18,"destAmount":"999497","srcAmount":"1000000000000000000","srcUSD":"1.0010000000","maxImpactReached":false,"priceUsd":"1.0004964970"}},{"chainId":42161,"address":"0x9d2f299715d94d8a7e6f5eaa8e654e8c74a988a7","name":"Frax Share","symbol":"FXS","decimals":18,"logoURI":"https://assets.coingecko.com/coins/images/13423/thumb/frax_share.png?1608478989","dexguru":{"address":"0x9d2f299715d94d8a7e6f5eaa8e654e8c74a988a7","volume_24h":0.016356762864015717,"liquidity":1.3135596067891,"volume_24h_usd":24.716452622396993,"liquidity_usd":1863.8070447737,"price_usd":5.687205803234598,"volume_24h_delta":-1,"liquidity_24h_delta":-0.05766198975191345,"price_24h_delta":-0.07007184953237884,"volume_24h_delta_usd":-1,"liquidity_24h_delta_usd":-0.013024499918304667,"price_24h_delta_usd":-0.026022200774690394,"timestamp":1658807160},"issue":"Inconsitent Liquidity"},{"chainId":42161,"address":"0x539bde0d7dbd336b79148aa742883198bbf60342","name":"Magic","symbol":"MAGIC","decimals":18,"logoURI":"https://assets.coingecko.com/coins/images/18623/thumb/magic.png?1656052146","dexscreener":{"priceUsd":"0.3054","source":"dexscreener","liquidity":7746713.061479431},"dexguru":{"address":"0x539bde0d7dbd336b79148aa742883198bbf60342","volume_24h":103.59026601173507,"liquidity":2721.0439719704,"volume_24h_usd":153816.04797615722,"liquidity_usd":3904323.5194655,"price_usd":0.3064919045928525,"volume_24h_delta":0.39098681132607505,"liquidity_24h_delta":-0.05783681895929031,"price_24h_delta":-0.10037764435477149,"volume_24h_delta_usd":0.31084602673954403,"liquidity_24h_delta_usd":-0.10650442369849093,"price_24h_delta_usd":-0.1468441195211927,"timestamp":1658808480},"paraswap":{"srcToken":"0x539bde0d7dbd336b79148aa742883198bbf60342","network":42161,"destToken":"0xfd086bc7cd5c481dcc9c85ebe478a1c0b69fcbb9","destDecimals":6,"srcDecimals":18,"destAmount":"329193","srcAmount":"1000000000000000000","srcUSD":"0.3025910000","maxImpactReached":false,"priceUsd":"0.3295221930"}},{"chainId":42161,"address":"0xfea7a6a0b346362bf88a9e4a88416b77a57d6c2a","name":"Magic Internet Money","symbol":"MIM","decimals":18,"logoURI":"https://assets.coingecko.com/coins/images/16786/thumb/mimlogopng.png?1624979612","dexscreener":{"priceUsd":"0.9935","source":"dexscreener","liquidity":3860863.93882558},"dexguru":{"address":"0xfea7a6a0b346362bf88a9e4a88416b77a57d6c2a","volume_24h":188.64924655353022,"liquidity":2289.2073285378,"volume_24h_usd":279570.6976113613,"liquidity_usd":3281581.9712935,"price_usd":0.9958004307447461,"volume_24h_delta":0.026727867303986182,"liquidity_24h_delta":0.0469154060283217,"price_24h_delta":0.05491628074447687,"volume_24h_delta_usd":-0.04431094273544695,"liquidity_24h_delta_usd":-0.012699640991108867,"price_24h_delta_usd":-0.006237708820248512,"timestamp":1658808480},"paraswap":{"srcToken":"0xfea7a6a0b346362bf88a9e4a88416b77a57d6c2a","network":42161,"destToken":"0xfd086bc7cd5c481dcc9c85ebe478a1c0b69fcbb9","destDecimals":6,"srcDecimals":18,"destAmount":"992108","srcAmount":"1000000000000000000","srcUSD":"0.9990940000","maxImpactReached":false,"priceUsd":"0.9931001080"}},{"chainId":42161,"address":"0xdb298285fe4c5410b05390ca80e8fbe9de1f259b","name":"handle fi","symbol":"FOREX","decimals":18,"logoURI":"https://assets.coingecko.com/coins/images/18533/thumb/handle.fiFOREXLogoDark200x200.png?1632755675","dexguru":{"address":"0xdb298285fe4c5410b05390ca80e8fbe9de1f259b","volume_24h":0.22238339240292604,"liquidity":5.7531966197453,"volume_24h_usd":355.28056889595,"liquidity_usd":8824.7245992303,"price_usd":0.010691709573488731,"volume_24h_delta":1,"liquidity_24h_delta":-0.03919979891136187,"price_24h_delta":-0.07697184776443657,"volume_24h_delta_usd":1,"liquidity_24h_delta_usd":-0.02385820009597697,"price_24h_delta_usd":-0.06223337498845065,"timestamp":1658713740},"issue":"Inconsitent Liquidity"},{"chainId":42161,"address":"0xfd086bc7cd5c481dcc9c85ebe478a1c0b69fcbb9","name":"Tether","symbol":"USDT","decimals":6,"logoURI":"https://assets.coingecko.com/coins/images/325/thumb/Tether-logo.png?1598003707","dexscreener":{"priceUsd":"0.9992","source":"dexscreener","liquidity":1821091},"dexguru":{"address":"0xfd086bc7cd5c481dcc9c85ebe478a1c0b69fcbb9","volume_24h":1308.9958678598568,"liquidity":44963.412588286,"volume_24h_usd":1964539.2748814528,"liquidity_usd":64624619.786171,"price_usd":0.999353,"volume_24h_delta":0.12536209351128896,"liquidity_24h_delta":0.041137965217388904,"price_24h_delta":0.05502675488756653,"volume_24h_delta_usd":0.05898101727090736,"liquidity_24h_delta_usd":-0.010887337195964537,"price_24h_delta_usd":-0.00005103041412673176,"timestamp":1658808480},"paraswap":{"srcToken":"0xfd086bc7cd5c481dcc9c85ebe478a1c0b69fcbb9","network":42161,"destToken":"0xfd086bc7cd5c481dcc9c85ebe478a1c0b69fcbb9","destDecimals":6,"srcDecimals":6,"destAmount":"999699","srcAmount":"1000000","srcUSD":"1.0010000000","maxImpactReached":false,"priceUsd":"1.0006986990"}},{"chainId":42161,"address":"0x377c6e37633e390aef9afb4f5e0b16689351eed4","name":"ZYX","symbol":"ZYX","decimals":18,"logoURI":"https://assets.coingecko.com/coins/images/11964/thumb/zyx.png?1596454904","dexguru":{"address":"0x377c6e37633e390aef9afb4f5e0b16689351eed4","volume_24h":0,"liquidity":0,"volume_24h_usd":0,"liquidity_usd":0,"price_usd":0.09138283704926257,"volume_24h_delta":-1,"liquidity_24h_delta":0,"price_24h_delta":0,"volume_24h_delta_usd":-1,"liquidity_24h_delta_usd":0,"price_24h_delta_usd":0,"timestamp":1645132083},"issue":"Inconsitent Liquidity"},{"chainId":42161,"address":"0x75c9bc761d88f70156daf83aa010e84680baf131","name":"Saddle Finance","symbol":"SDL","decimals":18,"logoURI":"https://assets.coingecko.com/coins/images/20476/thumb/saddle.PNG?1637113393","dexguru":{"address":"0x75c9bc761d88f70156daf83aa010e84680baf131","volume_24h":0,"liquidity":0,"volume_24h_usd":0,"liquidity_usd":0,"price_usd":0,"volume_24h_delta":0,"liquidity_24h_delta":0,"price_24h_delta":0,"volume_24h_delta_usd":0,"liquidity_24h_delta_usd":0,"price_24h_delta_usd":0,"timestamp":1656021361},"issue":"Inconsitent Liquidity"},{"chainId":42161,"address":"0xa943f863fa69ff4f6d9022843fb861bbee45b2ce","name":"Tangle","symbol":"TNGL","decimals":9,"logoURI":"https://assets.coingecko.com/coins/images/18312/thumb/tangle.PNG?1631510159","dexguru":{"address":"0xa943f863fa69ff4f6d9022843fb861bbee45b2ce","volume_24h":0,"liquidity":1.1150514609166,"volume_24h_usd":0,"liquidity_usd":1287.9996130219,"price_usd":0.000010072465743953481,"volume_24h_delta":0,"liquidity_24h_delta":0,"price_24h_delta":0,"volume_24h_delta_usd":0,"liquidity_24h_delta_usd":0,"price_24h_delta_usd":0,"timestamp":1656043620},"issue":"Inconsitent Liquidity"},{"chainId":42161,"address":"0x8d9ba570d6cb60c7e3e0f31343efe75ab8e65fb1","name":"Governance OHM","symbol":"GOHM","decimals":18,"logoURI":"https://assets.coingecko.com/coins/images/21129/thumb/token_wsOHM_logo.png?1638764900","dexscreener":{"priceUsd":"3006.41","source":"dexscreener","liquidity":2980063.919865948},"dexguru":{"address":"0x8d9ba570d6cb60c7e3e0f31343efe75ab8e65fb1","volume_24h":55.76305987504973,"liquidity":1522.659939383,"volume_24h_usd":81589.19281175056,"liquidity_usd":2209671.7701262,"price_usd":3004.673298314036,"volume_24h_delta":-0.6288054066707535,"liquidity_24h_delta":0.004675830787011085,"price_24h_delta":0.012792954797731548,"volume_24h_delta_usd":-0.6582589565264403,"liquidity_24h_delta_usd":-0.037823851622938026,"price_24h_delta_usd":-0.04981570283382486,"timestamp":1658806740},"paraswap":{"srcToken":"0x8d9ba570d6cb60c7e3e0f31343efe75ab8e65fb1","network":42161,"destToken":"0xfd086bc7cd5c481dcc9c85ebe478a1c0b69fcbb9","destDecimals":6,"srcDecimals":18,"destAmount":"2989850646","srcAmount":"1000000000000000000","srcUSD":"3017.4100000000","maxImpactReached":false,"priceUsd":"2992.8404966460"}},{"chainId":42161,"address":"0x55ff62567f09906a85183b866df84bf599a4bf70","name":"Kromatika","symbol":"KROM","decimals":18,"logoURI":"https://assets.coingecko.com/coins/images/20541/thumb/KROM_Transparent.png?1641398421","dexscreener":{"priceUsd":"0.0358","source":"dexscreener","liquidity":114145},"dexguru":{"address":"0x55ff62567f09906a85183b866df84bf599a4bf70","volume_24h":5.2412546818371215,"liquidity":34.037087608037,"volume_24h_usd":7806.4938600353535,"liquidity_usd":48137.71690787,"price_usd":0.03621050639813163,"volume_24h_delta":0.03001443822038802,"liquidity_24h_delta":-0.03196824548365769,"price_24h_delta":-0.0011421086572979142,"volume_24h_delta_usd":-0.0399747299810214,"liquidity_24h_delta_usd":-0.11828806608266627,"price_24h_delta_usd":-0.09021070953978133,"timestamp":1658797020},"paraswap":null},{"chainId":42161,"address":"0xf0a5717ec0883ee56438932b0fe4a20822735fba","name":"xToken","symbol":"XTK","decimals":18,"logoURI":"https://assets.coingecko.com/coins/images/14089/thumb/xtk_logo.png?1650508832","dexguru":{"address":"0xf0a5717ec0883ee56438932b0fe4a20822735fba","volume_24h":0,"liquidity":0.89729014290333,"volume_24h_usd":0,"liquidity_usd":1380.068862579,"price_usd":0.014245021472783306,"volume_24h_delta":0,"liquidity_24h_delta":0,"price_24h_delta":0,"volume_24h_delta_usd":0,"liquidity_24h_delta_usd":0,"price_24h_delta_usd":0,"timestamp":1658201820},"issue":"Inconsitent Liquidity"},{"chainId":42161,"address":"0x641441c631e2f909700d2f41fd87f0aa6a6b4edb","name":"dForce USD","symbol":"USX","decimals":18,"logoURI":"https://assets.coingecko.com/coins/images/17422/thumb/usx_32.png?1627600920","dexscreener":null,"dexguru":{"address":"0x641441c631e2f909700d2f41fd87f0aa6a6b4edb","volume_24h":41.42615816317676,"liquidity":377.04972268961,"volume_24h_usd":62200.81043053171,"liquidity_usd":542587.81735393,"price_usd":0.99365,"volume_24h_delta":186.83043422092092,"liquidity_24h_delta":0.21230114779788176,"price_24h_delta":0.10721028450174454,"volume_24h_delta_usd":175.18773497820877,"liquidity_24h_delta_usd":0.09380942782002896,"price_24h_delta_usd":-0.0019205232823268806,"timestamp":1658797020},"paraswap":null},{"chainId":42161,"address":"0x9b3fa2a7c3eb36d048a5d38d81e7fafc6bc47b25","name":"Aluna","symbol":"ALN","decimals":18,"logoURI":"https://assets.coingecko.com/coins/images/14379/thumb/uaLoLU8c_400x400_%281%29.png?1627873106","dexscreener":null,"dexguru":{"address":"0x9b3fa2a7c3eb36d048a5d38d81e7fafc6bc47b25","volume_24h":0,"liquidity":6.05,"volume_24h_usd":0,"liquidity_usd":24828.214539166,"price_usd":0.03426980178356195,"volume_24h_delta":0,"liquidity_24h_delta":0,"price_24h_delta":0,"volume_24h_delta_usd":0,"liquidity_24h_delta_usd":0,"price_24h_delta_usd":0,"timestamp":1640345949},"paraswap":{"srcToken":"0x9b3fa2a7c3eb36d048a5d38d81e7fafc6bc47b25","network":42161,"destToken":"0xfd086bc7cd5c481dcc9c85ebe478a1c0b69fcbb9","destDecimals":6,"srcDecimals":18,"destAmount":"4298496","srcAmount":"1000000000000000000","srcUSD":"0.0068501700","maxImpactReached":false,"priceUsd":"4.3027944960"}},{"chainId":42161,"address":"0x9fb9a33956351cf4fa040f65a13b835a3c8764e3","name":"Multichain","symbol":"MULTI","decimals":18,"logoURI":"https://assets.coingecko.com/coins/images/22087/thumb/1_Wyot-SDGZuxbjdkaOeT2-A.png?1640764238","dexguru":null,"issue":"Inconsitent Liquidity"},{"chainId":42161,"address":"0x488cc08935458403a0458e45e20c0159c8ab2c92","name":"Futureswap","symbol":"FST","decimals":18,"logoURI":"https://assets.coingecko.com/coins/images/14520/thumb/futureswap_logo.png?1634122916","dexguru":null,"issue":"Inconsitent Liquidity"},{"chainId":42161,"address":"0x5575552988a3a80504bbaeb1311674fcfd40ad4b","name":"Sperax","symbol":"SPA","decimals":18,"logoURI":"https://assets.coingecko.com/coins/images/12232/thumb/sperax_logo.jpg?1598342904","dexscreener":{"priceUsd":"0.004687","source":"dexscreener","liquidity":243758},"dexguru":{"address":"0x5575552988a3a80504bbaeb1311674fcfd40ad4b","volume_24h":0.31930245688716125,"liquidity":70.861315540237,"volume_24h_usd":486.5628183482328,"liquidity_usd":107584.68559093,"price_usd":0.004600846387068166,"volume_24h_delta":1,"liquidity_24h_delta":-0.004308322499128552,"price_24h_delta":-0.03685913586802162,"volume_24h_delta_usd":1,"liquidity_24h_delta_usd":-0.009696753983840277,"price_24h_delta_usd":-0.04109665070519009,"timestamp":1658779800},"paraswap":null},{"chainId":42161,"address":"0x6f5401c53e2769c858665621d22ddbf53d8d27c5","name":"Connect Financial","symbol":"CNFI","decimals":18,"logoURI":"https://assets.coingecko.com/coins/images/13592/thumb/cf-logo-iconic-black.png?1644479524","dexscreener":{"priceUsd":"0.1002","source":"dexscreener","liquidity":436286},"dexguru":{"address":"0x6f5401c53e2769c858665621d22ddbf53d8d27c5","volume_24h":4.918489767264195,"liquidity":127.29036473846,"volume_24h_usd":7397.014233676782,"liquidity_usd":192630.28801563,"price_usd":0.09988378331465758,"volume_24h_delta":0.16665252678643966,"liquidity_24h_delta":0.016210460862535667,"price_24h_delta":0.032449479106841816,"volume_24h_delta_usd":0.13068008224401675,"liquidity_24h_delta_usd":-0.037275663150733655,"price_24h_delta_usd":-0.021891351856484154,"timestamp":1658773140},"paraswap":null},{"chainId":42161,"address":"0x326c33fd1113c1f29b35b4407f3d6312a8518431","name":"Strips Finance","symbol":"STRP","decimals":18,"logoURI":"https://assets.coingecko.com/coins/images/18327/thumb/Logo-Strips-200-x-200px---without-words.png?1631543556","dexscreener":null,"dexguru":{"address":"0x326c33fd1113c1f29b35b4407f3d6312a8518431","volume_24h":2.4282160525243266,"liquidity":277.40793724348,"volume_24h_usd":3841.207829991612,"liquidity_usd":436818.895249,"price_usd":0.31354250777144405,"volume_24h_delta":1,"liquidity_24h_delta":-0.01027502838752163,"price_24h_delta":-0.018978269162830394,"volume_24h_delta_usd":1,"liquidity_24h_delta_usd":-0.0087674457207747,"price_24h_delta_usd":-0.01748394356781441,"timestamp":1658468400},"paraswap":{"srcToken":"0x326c33fd1113c1f29b35b4407f3d6312a8518431","network":42161,"destToken":"0xfd086bc7cd5c481dcc9c85ebe478a1c0b69fcbb9","destDecimals":6,"srcDecimals":18,"destAmount":"310864","srcAmount":"1000000000000000000","srcUSD":"0.3255520000","maxImpactReached":false,"priceUsd":"0.3111748640"}},{"chainId":42161,"address":"0xee9801669c6138e84bd50deb500827b776777d28","name":"O3 Swap","symbol":"O3","decimals":18,"logoURI":"https://assets.coingecko.com/coins/images/15460/thumb/o3.png?1620904316","dexscreener":{"priceUsd":"0.1525","source":"dexscreener","liquidity":171955.89637617115},"dexguru":{"address":"0xee9801669c6138e84bd50deb500827b776777d28","volume_24h":2.5353591570871035,"liquidity":20.000598984074,"volume_24h_usd":3969.472368306421,"liquidity_usd":30260.132867754,"price_usd":0.15528957761013,"volume_24h_delta":4.8373728880951035,"liquidity_24h_delta":0.09675757065851426,"price_24h_delta":0.13472800436391838,"volume_24h_delta_usd":4.798054746096948,"liquidity_24h_delta_usd":0.03502032760998497,"price_24h_delta_usd":0.07085337931131247,"timestamp":1658772300},"paraswap":{"srcToken":"0xee9801669c6138e84bd50deb500827b776777d28","network":42161,"destToken":"0xfd086bc7cd5c481dcc9c85ebe478a1c0b69fcbb9","destDecimals":6,"srcDecimals":18,"destAmount":"154798","srcAmount":"1000000000000000000","srcUSD":"0.1504800000","maxImpactReached":false,"priceUsd":"0.1549527980"}},{"chainId":42161,"address":"0x66ba30d5d7c66afd4ed41c3498ec9e20a03a1368","name":"eFIL","symbol":"EFIL","decimals":18,"logoURI":"https://assets.coingecko.com/coins/images/21379/thumb/bUkl8AZ4vHxogFQ.png?1639033822","dexscreener":null,"dexguru":{"address":"0x66ba30d5d7c66afd4ed41c3498ec9e20a03a1368","volume_24h":0,"liquidity":12.589512519112,"volume_24h_usd":0,"liquidity_usd":14492.508183763,"price_usd":5.462682829550925,"volume_24h_delta":-1,"liquidity_24h_delta":0,"price_24h_delta":0,"volume_24h_delta_usd":-1,"liquidity_24h_delta_usd":0,"price_24h_delta_usd":0,"timestamp":1656455580},"paraswap":null},{"chainId":42161,"address":"0x123389c2f0e9194d9ba98c21e63c375b67614108","name":"EthereumMax","symbol":"EMAX","decimals":18,"logoURI":"https://assets.coingecko.com/coins/images/15540/thumb/EMAX-Coin-Final2000x.png?1639402630","dexscreener":{"priceUsd":"0.000000004319","source":"dexscreener","liquidity":176248.39353862195},"dexguru":{"address":"0x123389c2f0e9194d9ba98c21e63c375b67614108","volume_24h":2.0183740668434207,"liquidity":57.680049814946,"volume_24h_usd":3240.4307077713847,"liquidity_usd":87910.141986633,"price_usd":4.31045633019618e-9,"volume_24h_delta":122.37178308418932,"liquidity_24h_delta":-0.02797544057850088,"price_24h_delta":-0.055268149819016996,"volume_24h_delta_usd":128.0449836766777,"liquidity_24h_delta_usd":-0.07254886074348639,"price_24h_delta_usd":-0.09859002815348615,"timestamp":1658726520},"paraswap":null},{"chainId":42161,"address":"0x6694340fc020c5e6b96567843da2df01b2ce1eb6","name":"Stargate Finance","symbol":"STG","decimals":18,"logoURI":"https://assets.coingecko.com/coins/images/24413/thumb/STG_LOGO.png?1647654518","dexguru":{"address":"0x6694340fc020c5e6b96567843da2df01b2ce1eb6","volume_24h":0,"liquidity":0,"volume_24h_usd":0,"liquidity_usd":0,"price_usd":2.9389568101428185e-27,"volume_24h_delta":0,"liquidity_24h_delta":0,"price_24h_delta":1,"volume_24h_delta_usd":0,"liquidity_24h_delta_usd":0,"price_24h_delta_usd":1,"timestamp":1648230068},"issue":"Inconsitent Liquidity"},{"chainId":42161,"address":"0x3f56e0c36d275367b8c502090edf38289b3dea0d","name":"MAI","symbol":"MIMATIC","decimals":18,"logoURI":"https://assets.coingecko.com/coins/images/15264/thumb/mimatic-red.png?1620281018","dexguru":{"address":"0x3f56e0c36d275367b8c502090edf38289b3dea0d","volume_24h":0,"liquidity":2.095344131475,"volume_24h_usd":0,"liquidity_usd":2312.434335,"price_usd":0.9803593789648412,"volume_24h_delta":0,"liquidity_24h_delta":0,"price_24h_delta":0,"volume_24h_delta_usd":0,"liquidity_24h_delta_usd":0,"price_24h_delta_usd":0,"timestamp":1656528960},"issue":"Inconsitent Liquidity"},{"chainId":42161,"address":"0x625e7708f30ca75bfd92586e17077590c60eb4cd","name":"Aave USDC","symbol":"AUSDC","decimals":6,"logoURI":"https://assets.coingecko.com/coins/images/14318/thumb/aUSDC.e260d492.png?1615527797","dexguru":{"address":"0x625e7708f30ca75bfd92586e17077590c60eb4cd","volume_24h":0,"liquidity":0,"volume_24h_usd":0,"liquidity_usd":0,"price_usd":0,"volume_24h_delta":0,"liquidity_24h_delta":0,"price_24h_delta":0,"volume_24h_delta_usd":0,"liquidity_24h_delta_usd":0,"price_24h_delta_usd":0,"timestamp":1650913929},"issue":"Inconsitent Liquidity"},{"chainId":42161,"address":"0x6ab707aca953edaefbc4fd23ba73294241490620","name":"Aave USDT","symbol":"AUSDT","decimals":6,"logoURI":"https://assets.coingecko.com/coins/images/14243/thumb/aUSDT.78f5faae.png?1615528400","dexguru":{"address":"0x6ab707aca953edaefbc4fd23ba73294241490620","volume_24h":0,"liquidity":0,"volume_24h_usd":0,"liquidity_usd":0,"price_usd":0,"volume_24h_delta":0,"liquidity_24h_delta":0,"price_24h_delta":0,"volume_24h_delta_usd":0,"liquidity_24h_delta_usd":0,"price_24h_delta_usd":0,"timestamp":1650913495},"issue":"Inconsitent Liquidity"},{"chainId":42161,"address":"0x82e64f49ed5ec1bc6e43dad4fc8af9bb3a2312ee","name":"Aave DAI","symbol":"ADAI","decimals":18,"logoURI":"https://assets.coingecko.com/coins/images/14242/thumb/aDAI.84b6c41f.png?1615528749","dexguru":{"address":"0x82e64f49ed5ec1bc6e43dad4fc8af9bb3a2312ee","volume_24h":0,"liquidity":0,"volume_24h_usd":0,"liquidity_usd":0,"price_usd":0,"volume_24h_delta":0,"liquidity_24h_delta":0,"price_24h_delta":0,"volume_24h_delta_usd":0,"liquidity_24h_delta_usd":0,"price_24h_delta_usd":0,"timestamp":1650913691},"issue":"Inconsitent Liquidity"},{"chainId":42161,"address":"0x191c10aa4af7c30e871e70c95db0e4eb77237530","name":"Aave LINK","symbol":"ALINK","decimals":18,"logoURI":"https://assets.coingecko.com/coins/images/14315/thumb/aLINK.412c6589.png?1615527827","dexguru":{"address":"0x191c10aa4af7c30e871e70c95db0e4eb77237530","volume_24h":0,"liquidity":0,"volume_24h_usd":0,"liquidity_usd":0,"price_usd":0,"volume_24h_delta":0,"liquidity_24h_delta":0,"price_24h_delta":0,"volume_24h_delta_usd":0,"liquidity_24h_delta_usd":0,"price_24h_delta_usd":0,"timestamp":1650913820},"issue":"Inconsitent Liquidity"},{"chainId":42161,"address":"0xe50fa9b3c56ffb159cb0fca61f5c9d750e8128c8","name":"Aave WETH","symbol":"AWETH","decimals":18,"logoURI":"https://assets.coingecko.com/coins/images/17238/thumb/aWETH_2x.png?1626940782","dexguru":{"address":"0xe50fa9b3c56ffb159cb0fca61f5c9d750e8128c8","volume_24h":0,"liquidity":0,"volume_24h_usd":0,"liquidity_usd":0,"price_usd":0,"volume_24h_delta":0,"liquidity_24h_delta":0,"price_24h_delta":0,"volume_24h_delta_usd":0,"liquidity_24h_delta_usd":0,"price_24h_delta_usd":0,"timestamp":1650913532},"issue":"Inconsitent Liquidity"},{"chainId":42161,"address":"0x078f358208685046a11c85e8ad32895ded33a249","name":"Aave WBTC","symbol":"AWBTC","decimals":8,"logoURI":"https://assets.coingecko.com/coins/images/14244/thumb/aWBTC.41453c2a.png?1615528721","dexguru":{"address":"0x078f358208685046a11c85e8ad32895ded33a249","volume_24h":0,"liquidity":0,"volume_24h_usd":0,"liquidity_usd":0,"price_usd":0,"volume_24h_delta":0,"liquidity_24h_delta":0,"price_24h_delta":0,"volume_24h_delta_usd":0,"liquidity_24h_delta_usd":0,"price_24h_delta_usd":0,"timestamp":1650913719},"issue":"Inconsitent Liquidity"},{"chainId":42161,"address":"0xebf1f92d4384118bfb91b4496660a95931c92861","name":"Aladdin cvxCRV","symbol":"ACRV","decimals":18,"logoURI":"https://assets.coingecko.com/coins/images/25395/thumb/Sv06cFHS_400x400.jpg?1651707422","dexguru":{"address":"0xebf1f92d4384118bfb91b4496660a95931c92861","volume_24h":0.5378292543795873,"liquidity":3.0913651749486,"volume_24h_usd":798.6432057560061,"liquidity_usd":4590.4862433178,"price_usd":1.4057991701305292,"volume_24h_delta":1,"liquidity_24h_delta":0.2910843617007494,"price_24h_delta":0.09367702230997614,"volume_24h_delta_usd":1,"liquidity_24h_delta_usd":0.29222645827143817,"price_24h_delta_usd":0.09464449183693235,"timestamp":1658779140},"issue":"Inconsitent Liquidity"},{"chainId":42161,"address":"0x0a3bb08b3a15a19b4de82f8acfc862606fb69a2d","name":"iZUMi Bond USD","symbol":"IUSD","decimals":18,"logoURI":"https://assets.coingecko.com/coins/images/25388/thumb/iusd-logo-symbol-10k%E5%A4%A7%E5%B0%8F.png?1651660620","dexguru":{"address":"0x0a3bb08b3a15a19b4de82f8acfc862606fb69a2d","volume_24h":0,"liquidity":4.8816732252277,"volume_24h_usd":0,"liquidity_usd":7383.1149570315,"price_usd":0.9985585006932843,"volume_24h_delta":-1,"liquidity_24h_delta":0,"price_24h_delta":0,"volume_24h_delta_usd":-1,"liquidity_24h_delta_usd":0,"price_24h_delta_usd":0,"timestamp":1658185080},"issue":"Inconsitent Liquidity"},{"chainId":42161,"address":"0x319f865b287fcc10b30d8ce6144e8b6d1b476999","name":"Cartesi","symbol":"CTSI","decimals":18,"logoURI":"https://assets.coingecko.com/coins/images/11038/thumb/cartesi.png?1592288021","dexguru":{"address":"0x319f865b287fcc10b30d8ce6144e8b6d1b476999","volume_24h":0,"liquidity":0,"volume_24h_usd":0,"liquidity_usd":0,"price_usd":0,"volume_24h_delta":0,"liquidity_24h_delta":0,"price_24h_delta":0,"volume_24h_delta_usd":0,"liquidity_24h_delta_usd":0,"price_24h_delta_usd":0,"timestamp":1654494817},"issue":"Inconsitent Liquidity"},{"chainId":42161,"address":"0xf0dfad1817b5ba73726b02ab34dd4b4b00bcd392","name":"Minato","symbol":"MNTO","decimals":18,"logoURI":"https://assets.coingecko.com/coins/images/24622/thumb/MNTO_200x200.png?1648448664","dexguru":{"address":"0xf0dfad1817b5ba73726b02ab34dd4b4b00bcd392","volume_24h":0,"liquidity":0,"volume_24h_usd":0,"liquidity_usd":0,"price_usd":11.845880381712814,"volume_24h_delta":-1,"liquidity_24h_delta":0,"price_24h_delta":0,"volume_24h_delta_usd":-1,"liquidity_24h_delta_usd":0,"price_24h_delta_usd":0,"timestamp":1650065317},"issue":"Inconsitent Liquidity"},{"chainId":42161,"address":"0x3bd2dfd03bc7c3011ed7fb8c4d0949b382726cee","name":"Roobee","symbol":"ROOBEE","decimals":18,"logoURI":"https://assets.coingecko.com/coins/images/8791/thumb/Group_11.png?1580344629","dexguru":null,"issue":"Inconsitent Liquidity"},{"chainId":42161,"address":"0x21e60ee73f17ac0a411ae5d690f908c3ed66fe12","name":"Deri Protocol","symbol":"DERI","decimals":18,"logoURI":"https://assets.coingecko.com/coins/images/13931/thumb/200vs200.jpg?1627649443","dexguru":null,"issue":"Inconsitent Liquidity"},{"chainId":42161,"address":"0xdc7179416c08c15f689d9214a3bec2dd003deabc","name":"KillSwitch","symbol":"KSW","decimals":18,"logoURI":"https://assets.coingecko.com/coins/images/20215/thumb/logo_%2824%29.png?1636670633","dexguru":{"address":"0xdc7179416c08c15f689d9214a3bec2dd003deabc","volume_24h":0,"liquidity":0.61586234826293,"volume_24h_usd":0,"liquidity_usd":1238.6039448148,"price_usd":0.04166741579275852,"volume_24h_delta":-1,"liquidity_24h_delta":0,"price_24h_delta":0,"volume_24h_delta_usd":-1,"liquidity_24h_delta_usd":0,"price_24h_delta_usd":0,"timestamp":1637641806},"issue":"Inconsitent Liquidity"},{"chainId":42161,"address":"0x68ead55c258d6fa5e46d67fc90f53211eab885be","name":"Popcorn","symbol":"POP","decimals":18,"logoURI":"https://assets.coingecko.com/coins/images/21438/thumb/pop.png?1644054028","dexguru":{"address":"0x68ead55c258d6fa5e46d67fc90f53211eab885be","volume_24h":0,"liquidity":0,"volume_24h_usd":0,"liquidity_usd":0,"price_usd":0,"volume_24h_delta":0,"liquidity_24h_delta":0,"price_24h_delta":0,"volume_24h_delta_usd":0,"liquidity_24h_delta_usd":0,"price_24h_delta_usd":0,"timestamp":1650913835},"issue":"Inconsitent Liquidity"},{"chainId":42161,"address":"0xc72633f995e98ac3bb8a89e6a9c4af335c3d6e44","name":"Omnisea","symbol":"OSEA","decimals":18,"logoURI":"https://assets.coingecko.com/coins/images/26475/thumb/293837892_407994084681555_3167689470652146992_n.png?1658195766","dexguru":null,"issue":"Inconsitent Liquidity"}]